{"name":"HMD-Workroom","groupName":"Unit 1","serialNo":"8A3-V6WS","History":[{"timestamp":"2025-08-30T00:00","system":"Auto","heatSetting":50,"coolSetting":95,"fan":"Auto","status":"Occupied","temperature":75.6,"humidity":0,"humidifySetting":0,"dehumidifySetting":0,"co2Setting":"","co2Level":"0","setBy":"Schedule","frontKeypad":"On","runStatus":"Off","auxStatus":"Off","setback":"Off"},{"timestamp":"2025-08-30T00:11","system":"Auto","heatSetting":50,"coolSetting":95,"fan":"Auto","status":"Occupied","temperature":75.7,"humidity":0,"humidifySetting":0,"dehumidifySetting":0,"co2Setting":"","co2Level":"0","setBy":"Schedule","frontKeypad":"On","runStatus":"Off","auxStatus":"Off","setback":"Off"},{"timestamp":"2025-08-30T00:25","system":"Auto","heatSetting":50,"coolSetting":95,"fan":"Auto","status":"Occupied","temperature":75.8,"humidity":0,"humidifySetting":0,"dehumidifySetting":0,"co2Setting":"","co2Level":"0","setBy":"Schedule","frontKeypad":"On","runStatus":"Off","auxStatus":"Off","setback":"Off"},{"timestamp":"2025-08-30T00:42","system":"Auto","heatSetting":50,"coolSetting":95,"fan":"Auto","status":"Occupied","temperature":76,"humidity":0,"humidifySetting":0,"dehumidifySetting":0,"co2Setting":"","co2Level":"0","setBy":"Schedule","frontKeypad":"On","runStatus":"Off","auxStatus":"Off","setback":"Off"},{"timestamp":"2025-08-30T01:01","system":"Auto","heatSetting":50,"coolSetting":95,"fan":"Auto","status":"Occupied","temperature":76.1,"humidity":0,"humidifySetting":0,"dehumidifySetting":0,"co2Setting":"","co2Level":"0","setBy":"Schedule","frontKeypad":"On","runStatus":"Off","auxStatus":"Off","setback":"Off"},{"timestamp":"2025-08-30T01:20","system":"Auto","heatSetting":50,"coolSetting":95,"fan":"Auto","status":"Occupied","temperature":76.2,"humidity":0,"humidifySetting":0,"dehumidifySetting":0,"co2Setting":"","co2Level":"0","setBy":"Schedule","frontKeypad":"On","runStatus":"Off","auxStatus":"Off","setback":"Off"},{"timestamp":"2025-08-30T01:26","system":"Auto","heatSetting":50,"coolSetting":95,"fan":"Auto","status":"Occupied","temperature":76.1,"humidity":0,"humidifySetting":0,"dehumidifySetting":0,"co2Setting":"","co2Level":"0","setBy":"Schedule","frontKeypad":"On","runStatus":"Off","auxStatus":"Off","setback":"Off"},{"timestamp":"2025-08-30T01:31","system":"Auto","heatSetting":50,"coolSetting":95,"fan":"Auto","status":"Occupied","temperature":76.2,"humidity":0,"humidifySetting":0,"dehumidifySetting":0,"co2Setting":"","co2Level":"0","setBy":"Schedule","frontKeypad":"On","runStatus":"Off","auxStatus":"Off","setback":"Off"},{"timestamp":"2025-08-30T01:50","system":"Auto","heatSetting":50,"coolSetting":95,"fan":"Auto","status":"Occupied","temperature":76.3,"humidity":0,"humidifySetting":0,"dehumidifySetting":0,"co2Setting":"","co2Level":"0","setBy":"Schedule","frontKeypad":"On","runStatus":"Off","auxStatus":"Off","setback":"Off"},{"timestamp":"2025-08-30T01:59","system":"Auto","heatSetting":50,"coolSetting":95,"fan":"Auto","status":"Occupied","temperature":76.3,"humidity":0,"humidifySetting":0,"dehumidifySetting":0,"co2Setting":"","co2Level":"0","setBy":"Schedule","frontKeypad":"On","runStatus":"Off","auxStatus":"Off","setback":"Off"},{"timestamp":"2025-08-30T02:23","system":"Auto","heatSetting":50,"coolSetting":95,"fan":"Auto","status":"Occupied","temperature":76.4,"humidity":0,"humidifySetting":0,"dehumidifySetting":0,"co2Setting":"","co2Level":"","setBy":"Schedule","frontKeypad":"On","runStatus":"Off","auxStatus":"Off","setback":"Off"},{"timestamp":"2025-08-30T02:28","system":"Auto","heatSetting":50,"coolSetting":95,"fan":"Auto","status":"Occupied","temperature":76.3,"humidity":0,"humidifySetting":0,"dehumidifySetting":0,"co2Setting":"","co2Level":"","setBy":"Schedule","frontKeypad":"On","runStatus":"Off","auxStatus":"Off","setback":"Off"},{"timestamp":"2025-08-30T02:34","system":"Auto","heatSetting":50,"coolSetting":95,"fan":"Auto","status":"Occupied","temperature":76.4,"humidity":0,"humidifySetting":0,"dehumidifySetting":0,"co2Setting":"","co2Level":"","setBy":"Schedule","frontKeypad":"On","runStatus":"Off","auxStatus":"Off","setback":"Off"},{"timestamp":"2025-08-30T03:06","system":"Auto","heatSetting":50,"coolSetting":95,"fan":"Auto","status":"Occupied","temperature":76.5,"humidity":0,"humidifySetting":0,"dehumidifySetting":0,"co2Setting":"","co2Level":"","setBy":"Schedule","frontKeypad":"On","runStatus":"Off","auxStatus":"Off","setback":"Off"},{"timestamp":"2025-08-30T03:10","system":"Auto","heatSetting":50,"coolSetting":95,"fan":"Auto","status":"Occupied","temperature":76.4,"humidity":0,"humidifySetting":0,"dehumidifySetting":0,"co2Setting":"","co2Level":"","setBy":"Schedule","frontKeypad":"On","runStatus":"Off","auxStatus":"Off","setback":"Off"},{"timestamp":"2025-08-30T03:19","system":"Auto","heatSetting":50,"coolSetting":95,"fan":"Auto","status":"Occupied","temperature":76.5,"humidity":0,"humidifySetting":0,"dehumidifySetting":0,"co2Setting":"","co2Level":"","setBy":"Schedule","frontKeypad":"On","runStatus":"Off","auxStatus":"Off","setback":"Off"},{"timestamp":"2025-08-30T04:19","system":"Auto","heatSetting":50,"coolSetting":95,"fan":"Auto","status":"Occupied","temperature":76.5,"humidity":0,"humidifySetting":0,"dehumidifySetting":0,"co2Setting":"","co2Level":"","setBy":"Schedule","frontKeypad":"On","runStatus":"Off","auxStatus":"Off","setback":"Off"},{"timestamp":"2025-08-30T05:10","system":"Auto","heatSetting":50,"coolSetting":95,"fan":"Auto","status":"Occupied","temperature":76.4,"humidity":0,"humidifySetting":0,"dehumidifySetting":0,"co2Setting":"","co2Level":"","setBy":"Schedule","frontKeypad":"On","runStatus":"Off","auxStatus":"Off","setback":"Off"},{"timestamp":"2025-08-30T05:15","system":"Auto","heatSetting":50,"coolSetting":95,"fan":"Auto","status":"Occupied","temperature":76.5,"humidity":0,"humidifySetting":0,"dehumidifySetting":0,"co2Setting":"","co2Level":"","setBy":"Schedule","frontKeypad":"On","runStatus":"Off","auxStatus":"Off","setback":"Off"},{"timestamp":"2025-08-30T05:20","system":"Auto","heatSetting":50,"coolSetting":95,"fan":"Auto","status":"Occupied","temperature":76.4,"humidity":0,"humidifySetting":0,"dehumidifySetting":0,"co2Setting":"","co2Level":"","setBy":"Schedule","frontKeypad":"On","runStatus":"Off","auxStatus":"Off","setback":"Off"},{"timestamp":"2025-08-30T05:25","system":"Auto","heatSetting":50,"coolSetting":95,"fan":"Auto","status":"Occupied","temperature":76.5,"humidity":0,"humidifySetting":0,"dehumidifySetting":0,"co2Setting":"","co2Level":"","setBy":"Schedule","frontKeypad":"On","runStatus":"Off","auxStatus":"Off","setback":"Off"},{"timestamp":"2025-08-30T05:31","system":"Auto","heatSetting":50,"coolSetting":95,"fan":"Auto","status":"Occupied","temperature":76.4,"humidity":0,"humidifySetting":0,"dehumidifySetting":0,"co2Setting":"","co2Level":"","setBy":"Schedule","frontKeypad":"On","runStatus":"Off","auxStatus":"Off","setback":"Off"},{"timestamp":"2025-08-30T05:36","system":"Auto","heatSetting":50,"coolSetting":95,"fan":"Auto","status":"Occupied","temperature":76.5,"humidity":0,"humidifySetting":0,"dehumidifySetting":0,"co2Setting":"","co2Level":"","setBy":"Schedule","frontKeypad":"On","runStatus":"Off","auxStatus":"Off","setback":"Off"},{"timestamp":"2025-08-30T05:45","system":"Auto","heatSetting":50,"coolSetting":95,"fan":"Auto","status":"Occupied","temperature":76.4,"humidity":0,"humidifySetting":0,"dehumidifySetting":0,"co2Setting":"","co2Level":"","setBy":"Schedule","frontKeypad":"On","runStatus":"Off","auxStatus":"Off","setback":"Off"},{"timestamp":"2025-08-30T06:00","system":"Auto","heatSetting":50,"coolSetting":95,"fan":"Auto","status":"Occupied","temperature":76.4,"humidity":0,"humidifySetting":0,"dehumidifySetting":0,"co2Setting":"","co2Level":"","setBy":"Schedule","frontKeypad":"On","runStatus":"Off","auxStatus":"Off","setback":"Off"},{"timestamp":"2025-08-30T06:02","system":"Auto","heatSetting":50,"coolSetting":95,"fan":"Auto","status":"Occupied","temperature":76.5,"humidity":0,"humidifySetting":0,"dehumidifySetting":0,"co2Setting":"","co2Level":"","setBy":"Schedule","frontKeypad":"On","runStatus":"Off","auxStatus":"Off","setback":"Off"},{"timestamp":"2025-08-30T06:07","system":"Auto","heatSetting":50,"coolSetting":95,"fan":"Auto","status":"Occupied","temperature":76.4,"humidity":0,"humidifySetting":0,"dehumidifySetting":0,"co2Setting":"","co2Level":"","setBy":"Schedule","frontKeypad":"On","runStatus":"Off","auxStatus":"Off","setback":"Off"},{"timestamp":"2025-08-30T06:16","system":"Auto","heatSetting":50,"coolSetting":95,"fan":"Auto","status":"Occupied","temperature":76.5,"humidity":0,"humidifySetting":0,"dehumidifySetting":0,"co2Setting":"","co2Level":"","setBy":"Schedule","frontKeypad":"On","runStatus":"Off","auxStatus":"Off","setback":"Off"},{"timestamp":"2025-08-30T06:21","system":"Auto","heatSetting":50,"coolSetting":95,"fan":"Auto","status":"Occupied","temperature":76.4,"humidity":0,"humidifySetting":0,"dehumidifySetting":0,"co2Setting":"","co2Level":"","setBy":"Schedule","frontKeypad":"On","runStatus":"Off","auxStatus":"Off","setback":"Off"},{"timestamp":"2025-08-30T07:13","system":"Auto","heatSetting":50,"coolSetting":95,"fan":"Auto","status":"Occupied","temperature":76.3,"humidity":0,"humidifySetting":0,"dehumidifySetting":0,"co2Setting":"","co2Level":"","setBy":"Schedule","frontKeypad":"On","runStatus":"Off","auxStatus":"Off","setback":"Off"},{"timestamp":"2025-08-30T07:17","system":"Auto","heatSetting":50,"coolSetting":95,"fan":"Auto","status":"Occupied","temperature":76.4,"humidity":0,"humidifySetting":0,"dehumidifySetting":0,"co2Setting":"","co2Level":"","setBy":"Schedule","frontKeypad":"On","runStatus":"Off","auxStatus":"Off","setback":"Off"},{"timestamp":"2025-08-30T07:23","system":"Auto","heatSetting":50,"coolSetting":95,"fan":"Auto","status":"Occupied","temperature":76.3,"humidity":0,"humidifySetting":0,"dehumidifySetting":0,"co2Setting":"","co2Level":"","setBy":"Schedule","frontKeypad":"On","runStatus":"Off","auxStatus":"Off","setback":"Off"},{"timestamp":"2025-08-30T08:00","system":"Auto","heatSetting":50,"coolSetting":95,"fan":"Auto","status":"Occupied","temperature":76.3,"humidity":0,"humidifySetting":0,"dehumidifySetting":0,"co2Setting":"","co2Level":"","setBy":"Schedule","frontKeypad":"On","runStatus":"Off","auxStatus":"Off","setback":"Off"},{"timestamp":"2025-08-30T08:23","system":"Auto","heatSetting":50,"coolSetting":95,"fan":"Auto","status":"Occupied","temperature":76.3,"humidity":0,"humidifySetting":0,"dehumidifySetting":0,"co2Setting":"","co2Level":"","setBy":"Schedule","frontKeypad":"On","runStatus":"Off","auxStatus":"Off","setback":"Off"},{"timestamp":"2025-08-30T09:09","system":"Auto","heatSetting":50,"coolSetting":95,"fan":"Auto","status":"Occupied","temperature":76.4,"humidity":0,"humidifySetting":0,"dehumidifySetting":0,"co2Setting":"","co2Level":"","setBy":"Schedule","frontKeypad":"On","runStatus":"Off","auxStatus":"Off","setback":"Off"},{"timestamp":"2025-08-30T09:37","system":"Auto","heatSetting":50,"coolSetting":95,"fan":"Auto","status":"Occupied","temperature":76.5,"humidity":0,"humidifySetting":0,"dehumidifySetting":0,"co2Setting":"","co2Level":"","setBy":"Schedule","frontKeypad":"On","runStatus":"Off","auxStatus":"Off","setback":"Off"},{"timestamp":"2025-08-30T09:58","system":"Auto","heatSetting":50,"coolSetting":95,"fan":"Auto","status":"Occupied","temperature":76.6,"humidity":0,"humidifySetting":0,"dehumidifySetting":0,"co2Setting":"","co2Level":"","setBy":"Schedule","frontKeypad":"On","runStatus":"Off","auxStatus":"Off","setback":"Off"},{"timestamp":"2025-08-30T10:16","system":"Auto","heatSetting":50,"coolSetting":95,"fan":"Auto","status":"Occupied","temperature":76.7,"humidity":0,"humidifySetting":0,"dehumidifySetting":0,"co2Setting":"","co2Level":"","setBy":"Schedule","frontKeypad":"On","runStatus":"Off","auxStatus":"Off","setback":"Off"},{"timestamp":"2025-08-30T10:35","system":"Auto","heatSetting":50,"coolSetting":95,"fan":"Auto","status":"Occupied","temperature":76.9,"humidity":0,"humidifySetting":0,"dehumidifySetting":0,"co2Setting":"","co2Level":"","setBy":"Schedule","frontKeypad":"On","runStatus":"Off","auxStatus":"Off","setback":"Off"},{"timestamp":"2025-08-30T10:44","system":"Auto","heatSetting":50,"coolSetting":95,"fan":"Auto","status":"Occupied","temperature":77,"humidity":0,"humidifySetting":0,"dehumidifySetting":0,"co2Setting":"","co2Level":"","setBy":"Schedule","frontKeypad":"On","runStatus":"Off","auxStatus":"Off","setback":"Off"},{"timestamp":"2025-08-30T11:00","system":"Auto","heatSetting":50,"coolSetting":95,"fan":"Auto","status":"Occupied","temperature":77.1,"humidity":0,"humidifySetting":0,"dehumidifySetting":0,"co2Setting":"","co2Level":"","setBy":"Schedule","frontKeypad":"On","runStatus":"Off","auxStatus":"Off","setback":"Off"},{"timestamp":"2025-08-30T11:15","system":"Auto","heatSetting":50,"coolSetting":95,"fan":"Auto","status":"Occupied","temperature":77.2,"humidity":0,"humidifySetting":0,"dehumidifySetting":0,"co2Setting":"","co2Level":"","setBy":"Schedule","frontKeypad":"On","runStatus":"Off","auxStatus":"Off","setback":"Off"},{"timestamp":"2025-08-30T11:27","system":"Auto","heatSetting":50,"coolSetting":95,"fan":"Auto","status":"Occupied","temperature":77.3,"humidity":0,"humidifySetting":0,"dehumidifySetting":0,"co2Setting":"","co2Level":"","setBy":"Schedule","frontKeypad":"On","runStatus":"Off","auxStatus":"Off","setback":"Off"},{"timestamp":"2025-08-30T11:40","system":"Auto","heatSetting":50,"coolSetting":95,"fan":"Auto","status":"Occupied","temperature":77.4,"humidity":0,"humidifySetting":0,"dehumidifySetting":0,"co2Setting":"","co2Level":"","setBy":"Schedule","frontKeypad":"On","runStatus":"Off","auxStatus":"Off","setback":"Off"},{"timestamp":"2025-08-30T11:48","system":"Auto","heatSetting":50,"coolSetting":95,"fan":"Auto","status":"Occupied","temperature":77.5,"humidity":0,"humidifySetting":0,"dehumidifySetting":0,"co2Setting":"","co2Level":"","setBy":"Schedule","frontKeypad":"On","runStatus":"Off","auxStatus":"Off","setback":"Off"},{"timestamp":"2025-08-30T12:00","system":"Auto","heatSetting":50,"coolSetting":95,"fan":"Auto","status":"Occupied","temperature":77.6,"humidity":0,"humidifySetting":0,"dehumidifySetting":0,"co2Setting":"","co2Level":"","setBy":"Schedule","frontKeypad":"On","runStatus":"Off","auxStatus":"Off","setback":"Off"},{"timestamp":"2025-08-30T12:12","system":"Auto","heatSetting":50,"coolSetting":95,"fan":"Auto","status":"Occupied","temperature":77.8,"humidity":0,"humidifySetting":0,"dehumidifySetting":0,"co2Setting":"","co2Level":"","setBy":"Schedule","frontKeypad":"On","runStatus":"Off","auxStatus":"Off","setback":"Off"},{"timestamp":"2025-08-30T12:18","system":"Auto","heatSetting":50,"coolSetting":95,"fan":"Auto","status":"Occupied","temperature":77.9,"humidity":0,"humidifySetting":0,"dehumidifySetting":0,"co2Setting":"","co2Level":"","setBy":"Schedule","frontKeypad":"On","runStatus":"Off","auxStatus":"Off","setback":"Off"},{"timestamp":"2025-08-30T12:26","system":"Auto","heatSetting":50,"coolSetting":95,"fan":"Auto","status":"Occupied","temperature":78,"humidity":0,"humidifySetting":0,"dehumidifySetting":0,"co2Setting":"","co2Level":"","setBy":"Schedule","frontKeypad":"On","runStatus":"Off","auxStatus":"Off","setback":"Off"},{"timestamp":"2025-08-30T12:36","system":"Auto","heatSetting":50,"coolSetting":95,"fan":"Auto","status":"Occupied","temperature":78.1,"humidity":0,"humidifySetting":0,"dehumidifySetting":0,"co2Setting":"","co2Level":"","setBy":"Schedule","frontKeypad":"On","runStatus":"Off","auxStatus":"Off","setback":"Off"},{"timestamp":"2025-08-30T12:44","system":"Auto","heatSetting":50,"coolSetting":95,"fan":"Auto","status":"Occupied","temperature":78.2,"humidity":0,"humidifySetting":0,"dehumidifySetting":0,"co2Setting":"","co2Level":"","setBy":"Schedule","frontKeypad":"On","runStatus":"Off","auxStatus":"Off","setback":"Off"},{"timestamp":"2025-08-30T12:51","system":"Auto","heatSetting":50,"coolSetting":95,"fan":"Auto","status":"Occupied","temperature":78.3,"humidity":0,"humidifySetting":0,"dehumidifySetting":0,"co2Setting":"","co2Level":"","setBy":"Schedule","frontKeypad":"On","runStatus":"Off","auxStatus":"Off","setback":"Off"},{"timestamp":"2025-08-30T13:04","system":"Auto","heatSetting":50,"coolSetting":95,"fan":"Auto","status":"Occupied","temperature":78.4,"humidity":0,"humidifySetting":0,"dehumidifySetting":0,"co2Setting":"","co2Level":"","setBy":"Schedule","frontKeypad":"On","runStatus":"Off","auxStatus":"Off","setback":"Off"},{"timestamp":"2025-08-30T13:09","system":"Auto","heatSetting":50,"coolSetting":95,"fan":"Auto","status":"Occupied","temperature":78.5,"humidity":0,"humidifySetting":0,"dehumidifySetting":0,"co2Setting":"","co2Level":"","setBy":"Schedule","frontKeypad":"On","runStatus":"Off","auxStatus":"Off","setback":"Off"},{"timestamp":"2025-08-30T13:20","system":"Auto","heatSetting":50,"coolSetting":95,"fan":"Auto","status":"Occupied","temperature":78.7,"humidity":0,"humidifySetting":0,"dehumidifySetting":0,"co2Setting":"","co2Level":"","setBy":"Schedule","frontKeypad":"On","runStatus":"Off","auxStatus":"Off","setback":"Off"},{"timestamp":"2025-08-30T13:26","system":"Auto","heatSetting":50,"coolSetting":95,"fan":"Auto","status":"Occupied","temperature":78.8,"humidity":0,"humidifySetting":0,"dehumidifySetting":0,"co2Setting":"","co2Level":"","setBy":"Schedule","frontKeypad":"On","runStatus":"Off","auxStatus":"Off","setback":"Off"},{"timestamp":"2025-08-30T13:33","system":"Auto","heatSetting":50,"coolSetting":95,"fan":"Auto","status":"Occupied","temperature":78.9,"humidity":0,"humidifySetting":0,"dehumidifySetting":0,"co2Setting":"","co2Level":"","setBy":"Schedule","frontKeypad":"On","runStatus":"Off","auxStatus":"Off","setback":"Off"},{"timestamp":"2025-08-30T13:43","system":"Auto","heatSetting":50,"coolSetting":95,"fan":"Auto","status":"Occupied","temperature":79,"humidity":0,"humidifySetting":0,"dehumidifySetting":0,"co2Setting":"","co2Level":"","setBy":"Schedule","frontKeypad":"On","runStatus":"Off","auxStatus":"Off","setback":"Off"},{"timestamp":"2025-08-30T13:50","system":"Auto","heatSetting":50,"coolSetting":95,"fan":"Auto","status":"Occupied","temperature":79.1,"humidity":0,"humidifySetting":0,"dehumidifySetting":0,"co2Setting":"","co2Level":"","setBy":"Schedule","frontKeypad":"On","runStatus":"Off","auxStatus":"Off","setback":"Off"},{"timestamp":"2025-08-30T13:59","system":"Auto","heatSetting":50,"coolSetting":95,"fan":"Auto","status":"Occupied","temperature":79.2,"humidity":0,"humidifySetting":0,"dehumidifySetting":0,"co2Setting":"","co2Level":"","setBy":"Schedule","frontKeypad":"On","runStatus":"Off","auxStatus":"Off","setback":"Off"},{"timestamp":"2025-08-30T14:05","system":"Auto","heatSetting":50,"coolSetting":95,"fan":"Auto","status":"Occupied","temperature":79.3,"humidity":0,"humidifySetting":0,"dehumidifySetting":0,"co2Setting":"","co2Level":"","setBy":"Schedule","frontKeypad":"On","runStatus":"Off","auxStatus":"Off","setback":"Off"},{"timestamp":"2025-08-30T14:14","system":"Auto","heatSetting":50,"coolSetting":95,"fan":"Auto","status":"Occupied","temperature":79.4,"humidity":0,"humidifySetting":0,"dehumidifySetting":0,"co2Setting":"","co2Level":"","setBy":"Schedule","frontKeypad":"On","runStatus":"Off","auxStatus":"Off","setback":"Off"},{"timestamp":"2025-08-30T14:23","system":"Auto","heatSetting":50,"coolSetting":95,"fan":"Auto","status":"Occupied","temperature":79.6,"humidity":0,"humidifySetting":0,"dehumidifySetting":0,"co2Setting":"","co2Level":"","setBy":"Schedule","frontKeypad":"On","runStatus":"Off","auxStatus":"Off","setback":"Off"},{"timestamp":"2025-08-30T14:30","system":"Auto","heatSetting":50,"coolSetting":95,"fan":"Auto","status":"Occupied","temperature":79.7,"humidity":0,"humidifySetting":0,"dehumidifySetting":0,"co2Setting":"","co2Level":"","setBy":"Schedule","frontKeypad":"On","runStatus":"Off","auxStatus":"Off","setback":"Off"},{"timestamp":"2025-08-30T14:35","system":"Auto","heatSetting":50,"coolSetting":95,"fan":"Auto","status":"Occupied","temperature":79.8,"humidity":0,"humidifySetting":0,"dehumidifySetting":0,"co2Setting":"","co2Level":"","setBy":"Schedule","frontKeypad":"On","runStatus":"Off","auxStatus":"Off","setback":"Off"},{"timestamp":"2025-08-30T14:44","system":"Auto","heatSetting":50,"coolSetting":95,"fan":"Auto","status":"Occupied","temperature":79.9,"humidity":0,"humidifySetting":0,"dehumidifySetting":0,"co2Setting":"","co2Level":"","setBy":"Schedule","frontKeypad":"On","runStatus":"Off","auxStatus":"Off","setback":"Off"},{"timestamp":"2025-08-30T14:52","system":"Auto","heatSetting":50,"coolSetting":95,"fan":"Auto","status":"Occupied","temperature":80,"humidity":0,"humidifySetting":0,"dehumidifySetting":0,"co2Setting":"","co2Level":"","setBy":"Schedule","frontKeypad":"On","runStatus":"Off","auxStatus":"Off","setback":"Off"},{"timestamp":"2025-08-30T15:00","system":"Auto","heatSetting":50,"coolSetting":95,"fan":"Auto","status":"Occupied","temperature":80.1,"humidity":0,"humidifySetting":0,"dehumidifySetting":0,"co2Setting":"","co2Level":"","setBy":"Schedule","frontKeypad":"On","runStatus":"Off","auxStatus":"Off","setback":"Off"},{"timestamp":"2025-08-30T15:08","system":"Auto","heatSetting":50,"coolSetting":95,"fan":"Auto","status":"Occupied","temperature":80.2,"humidity":0,"humidifySetting":0,"dehumidifySetting":0,"co2Setting":"","co2Level":"","setBy":"Schedule","frontKeypad":"On","runStatus":"Off","auxStatus":"Off","setback":"Off"},{"timestamp":"2025-08-30T15:15","system":"Auto","heatSetting":50,"coolSetting":95,"fan":"Auto","status":"Occupied","temperature":80.3,"humidity":0,"humidifySetting":0,"dehumidifySetting":0,"co2Setting":"","co2Level":"","setBy":"Schedule","frontKeypad":"On","runStatus":"Off","auxStatus":"Off","setback":"Off"},{"timestamp":"2025-08-30T15:24","system":"Auto","heatSetting":50,"coolSetting":95,"fan":"Auto","status":"Occupied","temperature":80.5,"humidity":0,"humidifySetting":0,"dehumidifySetting":0,"co2Setting":"","co2Level":"","setBy":"Schedule","frontKeypad":"On","runStatus":"Off","auxStatus":"Off","setback":"Off"},{"timestamp":"2025-08-30T15:31","system":"Auto","heatSetting":50,"coolSetting":95,"fan":"Auto","status":"Occupied","temperature":80.6,"humidity":0,"humidifySetting":0,"dehumidifySetting":0,"co2Setting":"","co2Level":"","setBy":"Schedule","frontKeypad":"On","runStatus":"Off","auxStatus":"Off","setback":"Off"},{"timestamp":"2025-08-30T15:38","system":"Auto","heatSetting":50,"coolSetting":95,"fan":"Auto","status":"Occupied","temperature":80.7,"humidity":0,"humidifySetting":0,"dehumidifySetting":0,"co2Setting":"","co2Level":"","setBy":"Schedule","frontKeypad":"On","runStatus":"Off","auxStatus":"Off","setback":"Off"},{"timestamp":"2025-08-30T15:46","system":"Auto","heatSetting":50,"coolSetting":95,"fan":"Auto","status":"Occupied","temperature":80.8,"humidity":0,"humidifySetting":0,"dehumidifySetting":0,"co2Setting":"","co2Level":"","setBy":"Schedule","frontKeypad":"On","runStatus":"Off","auxStatus":"Off","setback":"Off"},{"timestamp":"2025-08-30T15:54","system":"Auto","heatSetting":50,"coolSetting":95,"fan":"Auto","status":"Occupied","temperature":80.9,"humidity":0,"humidifySetting":0,"dehumidifySetting":0,"co2Setting":"","co2Level":"","setBy":"Schedule","frontKeypad":"On","runStatus":"Off","auxStatus":"Off","setback":"Off"},{"timestamp":"2025-08-30T16:02","system":"Auto","heatSetting":50,"coolSetting":95,"fan":"Auto","status":"Occupied","temperature":81,"humidity":0,"humidifySetting":0,"dehumidifySetting":0,"co2Setting":"","co2Level":"","setBy":"Schedule","frontKeypad":"On","runStatus":"Off","auxStatus":"Off","setback":"Off"},{"timestamp":"2025-08-30T16:11","system":"Auto","heatSetting":50,"coolSetting":95,"fan":"Auto","status":"Occupied","temperature":81.1,"humidity":0,"humidifySetting":0,"dehumidifySetting":0,"co2Setting":"","co2Level":"","setBy":"Schedule","frontKeypad":"On","runStatus":"Off","auxStatus":"Off","setback":"Off"},{"timestamp":"2025-08-30T16:20","system":"Auto","heatSetting":50,"coolSetting":95,"fan":"Auto","status":"Occupied","temperature":81.2,"humidity":0,"humidifySetting":0,"dehumidifySetting":0,"co2Setting":"","co2Level":"","setBy":"Schedule","frontKeypad":"On","runStatus":"Off","auxStatus":"Off","setback":"Off"},{"timestamp":"2025-08-30T16:30","system":"Auto","heatSetting":50,"coolSetting":95,"fan":"Auto","status":"Occupied","temperature":81.4,"humidity":0,"humidifySetting":0,"dehumidifySetting":0,"co2Setting":"","co2Level":"","setBy":"Schedule","frontKeypad":"On","runStatus":"Off","auxStatus":"Off","setback":"Off"},{"timestamp":"2025-08-30T16:36","system":"Auto","heatSetting":50,"coolSetting":95,"fan":"Auto","status":"Occupied","temperature":81.5,"humidity":0,"humidifySetting":0,"dehumidifySetting":0,"co2Setting":"","co2Level":"","setBy":"Schedule","frontKeypad":"On","runStatus":"Off","auxStatus":"Off","setback":"Off"},{"timestamp":"2025-08-30T16:49","system":"Auto","heatSetting":50,"coolSetting":95,"fan":"Auto","status":"Occupied","temperature":81.6,"humidity":0,"humidifySetting":0,"dehumidifySetting":0,"co2Setting":"","co2Level":"","setBy":"Schedule","frontKeypad":"On","runStatus":"Off","auxStatus":"Off","setback":"Off"},{"timestamp":"2025-08-30T16:59","system":"Auto","heatSetting":50,"coolSetting":95,"fan":"Auto","status":"Occupied","temperature":81.7,"humidity":0,"humidifySetting":0,"dehumidifySetting":0,"co2Setting":"","co2Level":"","setBy":"Schedule","frontKeypad":"On","runStatus":"Off","auxStatus":"Off","setback":"Off"},{"timestamp":"2025-08-30T17:07","system":"Auto","heatSetting":50,"coolSetting":95,"fan":"Auto","status":"Occupied","temperature":81.8,"humidity":0,"humidifySetting":0,"dehumidifySetting":0,"co2Setting":"","co2Level":"","setBy":"Schedule","frontKeypad":"On","runStatus":"Off","auxStatus":"Off","setback":"Off"},{"timestamp":"2025-08-30T17:18","system":"Auto","heatSetting":50,"coolSetting":95,"fan":"Auto","status":"Occupied","temperature":81.9,"humidity":0,"humidifySetting":0,"dehumidifySetting":0,"co2Setting":"","co2Level":"","setBy":"Schedule","frontKeypad":"On","runStatus":"Off","auxStatus":"Off","setback":"Off"},{"timestamp":"2025-08-30T17:32","system":"Auto","heatSetting":50,"coolSetting":95,"fan":"Auto","status":"Occupied","temperature":82,"humidity":0,"humidifySetting":0,"dehumidifySetting":0,"co2Setting":"","co2Level":"","setBy":"Schedule","frontKeypad":"On","runStatus":"Off","auxStatus":"Off","setback":"Off"},{"timestamp":"2025-08-30T17:43","system":"Auto","heatSetting":50,"coolSetting":95,"fan":"Auto","status":"Occupied","temperature":82.1,"humidity":0,"humidifySetting":0,"dehumidifySetting":0,"co2Setting":"","co2Level":"","setBy":"Schedule","frontKeypad":"On","runStatus":"Off","auxStatus":"Off","setback":"Off"},{"timestamp":"2025-08-30T17:57","system":"Auto","heatSetting":50,"coolSetting":95,"fan":"Auto","status":"Occupied","temperature":82.3,"humidity":0,"humidifySetting":0,"dehumidifySetting":0,"co2Setting":"","co2Level":"","setBy":"Schedule","frontKeypad":"On","runStatus":"Off","auxStatus":"Off","setback":"Off"},{"timestamp":"2025-08-30T18:13","system":"Auto","heatSetting":50,"coolSetting":95,"fan":"Auto","status":"Occupied","temperature":82.4,"humidity":0,"humidifySetting":0,"dehumidifySetting":0,"co2Setting":"","co2Level":"","setBy":"Schedule","frontKeypad":"On","runStatus":"Off","auxStatus":"Off","setback":"Off"},{"timestamp":"2025-08-30T18:30","system":"Auto","heatSetting":50,"coolSetting":95,"fan":"Auto","status":"Occupied","temperature":82.5,"humidity":0,"humidifySetting":0,"dehumidifySetting":0,"co2Setting":"","co2Level":"","setBy":"Schedule","frontKeypad":"On","runStatus":"Off","auxStatus":"Off","setback":"Off"},{"timestamp":"2025-08-30T18:52","system":"Auto","heatSetting":50,"coolSetting":95,"fan":"Auto","status":"Occupied","temperature":82.6,"humidity":0,"humidifySetting":0,"dehumidifySetting":0,"co2Setting":"","co2Level":"","setBy":"Schedule","frontKeypad":"On","runStatus":"Off","auxStatus":"Off","setback":"Off"},{"timestamp":"2025-08-30T19:22","system":"Auto","heatSetting":50,"coolSetting":95,"fan":"Auto","status":"Occupied","temperature":82.7,"humidity":0,"humidifySetting":0,"dehumidifySetting":0,"co2Setting":"","co2Level":"","setBy":"Schedule","frontKeypad":"On","runStatus":"Off","auxStatus":"Off","setback":"Off"},{"timestamp":"2025-08-30T19:27","system":"Auto","heatSetting":50,"coolSetting":95,"fan":"Auto","status":"Occupied","temperature":82.6,"humidity":0,"humidifySetting":0,"dehumidifySetting":0,"co2Setting":"","co2Level":"","setBy":"Schedule","frontKeypad":"On","runStatus":"Off","auxStatus":"Off","setback":"Off"},{"timestamp":"2025-08-30T19:32","system":"Auto","heatSetting":50,"coolSetting":95,"fan":"Auto","status":"Occupied","temperature":82.7,"humidity":0,"humidifySetting":0,"dehumidifySetting":0,"co2Setting":"","co2Level":"","setBy":"Schedule","frontKeypad":"On","runStatus":"Off","auxStatus":"Off","setback":"Off"},{"timestamp":"2025-08-30T20:32","system":"Auto","heatSetting":50,"coolSetting":95,"fan":"Auto","status":"Occupied","temperature":82.7,"humidity":0,"humidifySetting":0,"dehumidifySetting":0,"co2Setting":"","co2Level":"","setBy":"Schedule","frontKeypad":"On","runStatus":"Off","auxStatus":"Off","setback":"Off"},{"timestamp":"2025-08-30T20:45","system":"Auto","heatSetting":50,"coolSetting":95,"fan":"Auto","status":"Occupied","temperature":82.6,"humidity":0,"humidifySetting":0,"dehumidifySetting":0,"co2Setting":"","co2Level":"","setBy":"Schedule","frontKeypad":"On","runStatus":"Off","auxStatus":"Off","setback":"Off"},{"timestamp":"2025-08-30T20:52","system":"Auto","heatSetting":50,"coolSetting":95,"fan":"Auto","status":"Occupied","temperature":82.7,"humidity":0,"humidifySetting":0,"dehumidifySetting":0,"co2Setting":"","co2Level":"","setBy":"Schedule","frontKeypad":"On","runStatus":"Off","auxStatus":"Off","setback":"Off"},{"timestamp":"2025-08-30T20:57","system":"Auto","heatSetting":50,"coolSetting":95,"fan":"Auto","status":"Occupied","temperature":82.6,"humidity":0,"humidifySetting":0,"dehumidifySetting":0,"co2Setting":"","co2Level":"","setBy":"Schedule","frontKeypad":"On","runStatus":"Off","auxStatus":"Off","setback":"Off"},{"timestamp":"2025-08-30T21:24","system":"Auto","heatSetting":50,"coolSetting":95,"fan":"Auto","status":"Occupied","temperature":82.5,"humidity":0,"humidifySetting":0,"dehumidifySetting":0,"co2Setting":"","co2Level":"","setBy":"Schedule","frontKeypad":"On","runStatus":"Off","auxStatus":"Off","setback":"Off"},{"timestamp":"2025-08-30T21:47","system":"Auto","heatSetting":50,"coolSetting":95,"fan":"Auto","status":"Occupied","temperature":82.4,"humidity":0,"humidifySetting":0,"dehumidifySetting":0,"co2Setting":"","co2Level":"","setBy":"Schedule","frontKeypad":"On","runStatus":"Off","auxStatus":"Off","setback":"Off"},{"timestamp":"2025-08-30T21:52","system":"Auto","heatSetting":50,"coolSetting":95,"fan":"Auto","status":"Occupied","temperature":82.5,"humidity":0,"humidifySetting":0,"dehumidifySetting":0,"co2Setting":"","co2Level":"","setBy":"Schedule","frontKeypad":"On","runStatus":"Off","auxStatus":"Off","setback":"Off"},{"timestamp":"2025-08-30T21:57","system":"Auto","heatSetting":50,"coolSetting":95,"fan":"Auto","status":"Occupied","temperature":82.4,"humidity":0,"humidifySetting":0,"dehumidifySetting":0,"co2Setting":"","co2Level":"","setBy":"Schedule","frontKeypad":"On","runStatus":"Off","auxStatus":"Off","setback":"Off"},{"timestamp":"2025-08-30T22:07","system":"Auto","heatSetting":50,"coolSetting":95,"fan":"Auto","status":"Occupied","temperature":82.3,"humidity":0,"humidifySetting":0,"dehumidifySetting":0,"co2Setting":"","co2Level":"","setBy":"Schedule","frontKeypad":"On","runStatus":"Off","auxStatus":"Off","setback":"Off"},{"timestamp":"2025-08-30T22:24","system":"Auto","heatSetting":50,"coolSetting":95,"fan":"Auto","status":"Occupied","temperature":82.1,"humidity":0,"humidifySetting":0,"dehumidifySetting":0,"co2Setting":"","co2Level":"","setBy":"Schedule","frontKeypad":"On","runStatus":"Off","auxStatus":"Off","setback":"Off"},{"timestamp":"2025-08-30T22:29","system":"Auto","heatSetting":50,"coolSetting":95,"fan":"Auto","status":"Occupied","temperature":82.3,"humidity":0,"humidifySetting":0,"dehumidifySetting":0,"co2Setting":"","co2Level":"","setBy":"Schedule","frontKeypad":"On","runStatus":"Off","auxStatus":"Off","setback":"Off"},{"timestamp":"2025-08-30T22:34","system":"Auto","heatSetting":50,"coolSetting":95,"fan":"Auto","status":"Occupied","temperature":82.1,"humidity":0,"humidifySetting":0,"dehumidifySetting":0,"co2Setting":"","co2Level":"","setBy":"Schedule","frontKeypad":"On","runStatus":"Off","auxStatus":"Off","setback":"Off"},{"timestamp":"2025-08-30T22:47","system":"Auto","heatSetting":50,"coolSetting":95,"fan":"Auto","status":"Occupied","temperature":82,"humidity":0,"humidifySetting":0,"dehumidifySetting":0,"co2Setting":"","co2Level":"","setBy":"Schedule","frontKeypad":"On","runStatus":"Off","auxStatus":"Off","setback":"Off"},{"timestamp":"2025-08-30T22:59","system":"Auto","heatSetting":50,"coolSetting":95,"fan":"Auto","status":"Occupied","temperature":82,"humidity":0,"humidifySetting":0,"dehumidifySetting":0,"co2Setting":"","co2Level":"","setBy":"Schedule","frontKeypad":"On","runStatus":"Off","auxStatus":"Off","setback":"Off"},{"timestamp":"2025-08-30T23:03","system":"Auto","heatSetting":50,"coolSetting":95,"fan":"Auto","status":"Occupied","temperature":81.9,"humidity":0,"humidifySetting":0,"dehumidifySetting":0,"co2Setting":"","co2Level":"","setBy":"Schedule","frontKeypad":"On","runStatus":"Off","auxStatus":"Off","setback":"Off"},{"timestamp":"2025-08-30T23:06","system":"Auto","heatSetting":50,"coolSetting":95,"fan":"Auto","status":"Occupied","temperature":82,"humidity":0,"humidifySetting":0,"dehumidifySetting":0,"co2Setting":"","co2Level":"","setBy":"Schedule","frontKeypad":"On","runStatus":"Off","auxStatus":"Off","setback":"Off"},{"timestamp":"2025-08-30T23:08","system":"Auto","heatSetting":50,"coolSetting":95,"fan":"Auto","status":"Occupied","temperature":81.9,"humidity":0,"humidifySetting":0,"dehumidifySetting":0,"co2Setting":"","co2Level":"","setBy":"Schedule","frontKeypad":"On","runStatus":"Off","auxStatus":"Off","setback":"Off"},{"timestamp":"2025-08-30T23:20","system":"Auto","heatSetting":50,"coolSetting":95,"fan":"Auto","status":"Occupied","temperature":81.8,"humidity":0,"humidifySetting":0,"dehumidifySetting":0,"co2Setting":"","co2Level":"","setBy":"Schedule","frontKeypad":"On","runStatus":"Off","auxStatus":"Off","setback":"Off"},{"timestamp":"2025-08-30T23:36","system":"Auto","heatSetting":50,"coolSetting":95,"fan":"Auto","status":"Occupied","temperature":81.7,"humidity":0,"humidifySetting":0,"dehumidifySetting":0,"co2Setting":"","co2Level":"","setBy":"Schedule","frontKeypad":"On","runStatus":"Off","auxStatus":"Off","setback":"Off"},{"timestamp":"2025-08-30T23:53","system":"Auto","heatSetting":50,"coolSetting":95,"fan":"Auto","status":"Occupied","temperature":81.6,"humidity":0,"humidifySetting":0,"dehumidifySetting":0,"co2Setting":"","co2Level":"","setBy":"Schedule","frontKeypad":"On","runStatus":"Off","auxStatus":"Off","setback":"Off"},{"timestamp":"2025-08-31T00:13","system":"Auto","heatSetting":50,"coolSetting":95,"fan":"Auto","status":"Occupied","temperature":81.5,"humidity":0,"humidifySetting":0,"dehumidifySetting":0,"co2Setting":"","co2Level":"","setBy":"Schedule","frontKeypad":"On","runStatus":"Off","auxStatus":"Off","setback":"Off"},{"timestamp":"2025-08-31T00:29","system":"Auto","heatSetting":50,"coolSetting":95,"fan":"Auto","status":"Occupied","temperature":81.4,"humidity":0,"humidifySetting":0,"dehumidifySetting":0,"co2Setting":"","co2Level":"","setBy":"Schedule","frontKeypad":"On","runStatus":"Off","auxStatus":"Off","setback":"Off"},{"timestamp":"2025-08-31T00:40","system":"Auto","heatSetting":50,"coolSetting":95,"fan":"Auto","status":"Occupied","temperature":81.2,"humidity":0,"humidifySetting":0,"dehumidifySetting":0,"co2Setting":"","co2Level":"","setBy":"Schedule","frontKeypad":"On","runStatus":"Off","auxStatus":"Off","setback":"Off"},{"timestamp":"2025-08-31T00:54","system":"Auto","heatSetting":50,"coolSetting":95,"fan":"Auto","status":"Occupied","temperature":81.1,"humidity":0,"humidifySetting":0,"dehumidifySetting":0,"co2Setting":"","co2Level":"","setBy":"Schedule","frontKeypad":"On","runStatus":"Off","auxStatus":"Off","setback":"Off"},{"timestamp":"2025-08-31T01:10","system":"Auto","heatSetting":50,"coolSetting":95,"fan":"Auto","status":"Occupied","temperature":81,"humidity":0,"humidifySetting":0,"dehumidifySetting":0,"co2Setting":"","co2Level":"","setBy":"Schedule","frontKeypad":"On","runStatus":"Off","auxStatus":"Off","setback":"Off"},{"timestamp":"2025-08-31T01:27","system":"Auto","heatSetting":50,"coolSetting":95,"fan":"Auto","status":"Occupied","temperature":80.9,"humidity":0,"humidifySetting":0,"dehumidifySetting":0,"co2Setting":"","co2Level":"","setBy":"Schedule","frontKeypad":"On","runStatus":"Off","auxStatus":"Off","setback":"Off"},{"timestamp":"2025-08-31T01:32","system":"Auto","heatSetting":50,"coolSetting":95,"fan":"Auto","status":"Occupied","temperature":81,"humidity":0,"humidifySetting":0,"dehumidifySetting":0,"co2Setting":"","co2Level":"","setBy":"Schedule","frontKeypad":"On","runStatus":"Off","auxStatus":"Off","setback":"Off"},{"timestamp":"2025-08-31T01:34","system":"Auto","heatSetting":50,"coolSetting":95,"fan":"Auto","status":"Occupied","temperature":80.9,"humidity":0,"humidifySetting":0,"dehumidifySetting":0,"co2Setting":"","co2Level":"","setBy":"Schedule","frontKeypad":"On","runStatus":"Off","auxStatus":"Off","setback":"Off"},{"timestamp":"2025-08-31T01:41","system":"Auto","heatSetting":50,"coolSetting":95,"fan":"Auto","status":"Occupied","temperature":80.8,"humidity":0,"humidifySetting":0,"dehumidifySetting":0,"co2Setting":"","co2Level":"","setBy":"Schedule","frontKeypad":"On","runStatus":"Off","auxStatus":"Off","setback":"Off"},{"timestamp":"2025-08-31T01:56","system":"Auto","heatSetting":50,"coolSetting":95,"fan":"Auto","status":"Occupied","temperature":80.7,"humidity":0,"humidifySetting":0,"dehumidifySetting":0,"co2Setting":"","co2Level":"","setBy":"Schedule","frontKeypad":"On","runStatus":"Off","auxStatus":"Off","setback":"Off"},{"timestamp":"2025-08-31T02:10","system":"Auto","heatSetting":50,"coolSetting":95,"fan":"Auto","status":"Occupied","temperature":80.6,"humidity":0,"humidifySetting":0,"dehumidifySetting":0,"co2Setting":"","co2Level":"","setBy":"Schedule","frontKeypad":"On","runStatus":"Off","auxStatus":"Off","setback":"Off"},{"timestamp":"2025-08-31T02:25","system":"Auto","heatSetting":50,"coolSetting":95,"fan":"Auto","status":"Occupied","temperature":80.5,"humidity":0,"humidifySetting":0,"dehumidifySetting":0,"co2Setting":"","co2Level":"","setBy":"Schedule","frontKeypad":"On","runStatus":"Off","auxStatus":"Off","setback":"Off"},{"timestamp":"2025-08-31T02:37","system":"Auto","heatSetting":50,"coolSetting":95,"fan":"Auto","status":"Occupied","temperature":80.3,"humidity":0,"humidifySetting":0,"dehumidifySetting":0,"co2Setting":"","co2Level":"","setBy":"Schedule","frontKeypad":"On","runStatus":"Off","auxStatus":"Off","setback":"Off"},{"timestamp":"2025-08-31T02:55","system":"Auto","heatSetting":50,"coolSetting":95,"fan":"Auto","status":"Occupied","temperature":80.2,"humidity":0,"humidifySetting":0,"dehumidifySetting":0,"co2Setting":"","co2Level":"","setBy":"Schedule","frontKeypad":"On","runStatus":"Off","auxStatus":"Off","setback":"Off"},{"timestamp":"2025-08-31T03:10","system":"Auto","heatSetting":50,"coolSetting":95,"fan":"Auto","status":"Occupied","temperature":80.1,"humidity":0,"humidifySetting":0,"dehumidifySetting":0,"co2Setting":"","co2Level":"","setBy":"Schedule","frontKeypad":"On","runStatus":"Off","auxStatus":"Off","setback":"Off"},{"timestamp":"2025-08-31T03:25","system":"Auto","heatSetting":50,"coolSetting":95,"fan":"Auto","status":"Occupied","temperature":80,"humidity":0,"humidifySetting":0,"dehumidifySetting":0,"co2Setting":"","co2Level":"","setBy":"Schedule","frontKeypad":"On","runStatus":"Off","auxStatus":"Off","setback":"Off"},{"timestamp":"2025-08-31T03:45","system":"Auto","heatSetting":50,"coolSetting":95,"fan":"Auto","status":"Occupied","temperature":79.9,"humidity":0,"humidifySetting":0,"dehumidifySetting":0,"co2Setting":"","co2Level":"","setBy":"Schedule","frontKeypad":"On","runStatus":"Off","auxStatus":"Off","setback":"Off"},{"timestamp":"2025-08-31T04:03","system":"Auto","heatSetting":50,"coolSetting":95,"fan":"Auto","status":"Occupied","temperature":79.8,"humidity":0,"humidifySetting":0,"dehumidifySetting":0,"co2Setting":"","co2Level":"","setBy":"Schedule","frontKeypad":"On","runStatus":"Off","auxStatus":"Off","setback":"Off"},{"timestamp":"2025-08-31T04:18","system":"Auto","heatSetting":50,"coolSetting":95,"fan":"Auto","status":"Occupied","temperature":79.7,"humidity":0,"humidifySetting":0,"dehumidifySetting":0,"co2Setting":"","co2Level":"","setBy":"Schedule","frontKeypad":"On","runStatus":"Off","auxStatus":"Off","setback":"Off"},{"timestamp":"2025-08-31T04:39","system":"Auto","heatSetting":50,"coolSetting":95,"fan":"Auto","status":"Occupied","temperature":79.6,"humidity":0,"humidifySetting":0,"dehumidifySetting":0,"co2Setting":"","co2Level":"","setBy":"Schedule","frontKeypad":"On","runStatus":"Off","auxStatus":"Off","setback":"Off"},{"timestamp":"2025-08-31T04:50","system":"Auto","heatSetting":50,"coolSetting":95,"fan":"Auto","status":"Occupied","temperature":79.4,"humidity":0,"humidifySetting":0,"dehumidifySetting":0,"co2Setting":"","co2Level":"","setBy":"Schedule","frontKeypad":"On","runStatus":"Off","auxStatus":"Off","setback":"Off"},{"timestamp":"2025-08-31T05:09","system":"Auto","heatSetting":50,"coolSetting":95,"fan":"Auto","status":"Occupied","temperature":79.3,"humidity":0,"humidifySetting":0,"dehumidifySetting":0,"co2Setting":"","co2Level":"","setBy":"Schedule","frontKeypad":"On","runStatus":"Off","auxStatus":"Off","setback":"Off"},{"timestamp":"2025-08-31T05:25","system":"Auto","heatSetting":50,"coolSetting":95,"fan":"Auto","status":"Occupied","temperature":79.2,"humidity":0,"humidifySetting":0,"dehumidifySetting":0,"co2Setting":"","co2Level":"","setBy":"Schedule","frontKeypad":"On","runStatus":"Off","auxStatus":"Off","setback":"Off"},{"timestamp":"2025-08-31T05:47","system":"Auto","heatSetting":50,"coolSetting":95,"fan":"Auto","status":"Occupied","temperature":79.1,"humidity":0,"humidifySetting":0,"dehumidifySetting":0,"co2Setting":"","co2Level":"","setBy":"Schedule","frontKeypad":"On","runStatus":"Off","auxStatus":"Off","setback":"Off"},{"timestamp":"2025-08-31T06:00","system":"Auto","heatSetting":50,"coolSetting":95,"fan":"Auto","status":"Occupied","temperature":79.1,"humidity":0,"humidifySetting":0,"dehumidifySetting":0,"co2Setting":"","co2Level":"","setBy":"Schedule","frontKeypad":"On","runStatus":"Off","auxStatus":"Off","setback":"Off"},{"timestamp":"2025-08-31T06:03","system":"Auto","heatSetting":50,"coolSetting":95,"fan":"Auto","status":"Occupied","temperature":79,"humidity":0,"humidifySetting":0,"dehumidifySetting":0,"co2Setting":"","co2Level":"","setBy":"Schedule","frontKeypad":"On","runStatus":"Off","auxStatus":"Off","setback":"Off"},{"timestamp":"2025-08-31T06:09","system":"Auto","heatSetting":50,"coolSetting":95,"fan":"Auto","status":"Occupied","temperature":79.1,"humidity":0,"humidifySetting":0,"dehumidifySetting":0,"co2Setting":"","co2Level":"","setBy":"Schedule","frontKeypad":"On","runStatus":"Off","auxStatus":"Off","setback":"Off"},{"timestamp":"2025-08-31T06:14","system":"Auto","heatSetting":50,"coolSetting":95,"fan":"Auto","status":"Occupied","temperature":79,"humidity":0,"humidifySetting":0,"dehumidifySetting":0,"co2Setting":"","co2Level":"","setBy":"Schedule","frontKeypad":"On","runStatus":"Off","auxStatus":"Off","setback":"Off"},{"timestamp":"2025-08-31T06:23","system":"Auto","heatSetting":50,"coolSetting":95,"fan":"Auto","status":"Occupied","temperature":78.9,"humidity":0,"humidifySetting":0,"dehumidifySetting":0,"co2Setting":"","co2Level":"","setBy":"Schedule","frontKeypad":"On","runStatus":"Off","auxStatus":"Off","setback":"Off"},{"timestamp":"2025-08-31T06:28","system":"Auto","heatSetting":50,"coolSetting":95,"fan":"Auto","status":"Occupied","temperature":79,"humidity":0,"humidifySetting":0,"dehumidifySetting":0,"co2Setting":"","co2Level":"","setBy":"Schedule","frontKeypad":"On","runStatus":"Off","auxStatus":"Off","setback":"Off"},{"timestamp":"2025-08-31T06:30","system":"Auto","heatSetting":50,"coolSetting":95,"fan":"Auto","status":"Occupied","temperature":78.9,"humidity":0,"humidifySetting":0,"dehumidifySetting":0,"co2Setting":"","co2Level":"","setBy":"Schedule","frontKeypad":"On","runStatus":"Off","auxStatus":"Off","setback":"Off"},{"timestamp":"2025-08-31T06:45","system":"Auto","heatSetting":50,"coolSetting":95,"fan":"Auto","status":"Occupied","temperature":78.8,"humidity":0,"humidifySetting":0,"dehumidifySetting":0,"co2Setting":"","co2Level":"","setBy":"Schedule","frontKeypad":"On","runStatus":"Off","auxStatus":"Off","setback":"Off"},{"timestamp":"2025-08-31T07:05","system":"Auto","heatSetting":50,"coolSetting":95,"fan":"Auto","status":"Occupied","temperature":78.7,"humidity":0,"humidifySetting":0,"dehumidifySetting":0,"co2Setting":"","co2Level":"","setBy":"Schedule","frontKeypad":"On","runStatus":"Off","auxStatus":"Off","setback":"Off"},{"timestamp":"2025-08-31T07:25","system":"Auto","heatSetting":50,"coolSetting":95,"fan":"Auto","status":"Occupied","temperature":78.5,"humidity":0,"humidifySetting":0,"dehumidifySetting":0,"co2Setting":"","co2Level":"","setBy":"Schedule","frontKeypad":"On","runStatus":"Off","auxStatus":"Off","setback":"Off"},{"timestamp":"2025-08-31T07:57","system":"Auto","heatSetting":50,"coolSetting":95,"fan":"Auto","status":"Occupied","temperature":78.4,"humidity":0,"humidifySetting":0,"dehumidifySetting":0,"co2Setting":"","co2Level":"","setBy":"Schedule","frontKeypad":"On","runStatus":"Off","auxStatus":"Off","setback":"Off"},{"timestamp":"2025-08-31T08:00","system":"Auto","heatSetting":50,"coolSetting":95,"fan":"Auto","status":"Occupied","temperature":78.5,"humidity":0,"humidifySetting":0,"dehumidifySetting":0,"co2Setting":"","co2Level":"","setBy":"Schedule","frontKeypad":"On","runStatus":"Off","auxStatus":"Off","setback":"Off"},{"timestamp":"2025-08-31T08:02","system":"Auto","heatSetting":50,"coolSetting":95,"fan":"Auto","status":"Occupied","temperature":78.4,"humidity":0,"humidifySetting":0,"dehumidifySetting":0,"co2Setting":"","co2Level":"","setBy":"Schedule","frontKeypad":"On","runStatus":"Off","auxStatus":"Off","setback":"Off"},{"timestamp":"2025-08-31T08:38","system":"Auto","heatSetting":50,"coolSetting":95,"fan":"Auto","status":"Occupied","temperature":78.3,"humidity":0,"humidifySetting":0,"dehumidifySetting":0,"co2Setting":"","co2Level":"","setBy":"Schedule","frontKeypad":"On","runStatus":"Off","auxStatus":"Off","setback":"Off"},{"timestamp":"2025-08-31T08:43","system":"Auto","heatSetting":50,"coolSetting":95,"fan":"Auto","status":"Occupied","temperature":78.4,"humidity":0,"humidifySetting":0,"dehumidifySetting":0,"co2Setting":"","co2Level":"","setBy":"Schedule","frontKeypad":"On","runStatus":"Off","auxStatus":"Off","setback":"Off"},{"timestamp":"2025-08-31T08:50","system":"Auto","heatSetting":50,"coolSetting":95,"fan":"Auto","status":"Occupied","temperature":78.3,"humidity":0,"humidifySetting":0,"dehumidifySetting":0,"co2Setting":"","co2Level":"","setBy":"Schedule","frontKeypad":"On","runStatus":"Off","auxStatus":"Off","setback":"Off"},{"timestamp":"2025-08-31T09:03","system":"Auto","heatSetting":50,"coolSetting":95,"fan":"Auto","status":"Occupied","temperature":78.4,"humidity":0,"humidifySetting":0,"dehumidifySetting":0,"co2Setting":"","co2Level":"","setBy":"Schedule","frontKeypad":"On","runStatus":"Off","auxStatus":"Off","setback":"Off"},{"timestamp":"2025-08-31T09:08","system":"Auto","heatSetting":50,"coolSetting":95,"fan":"Auto","status":"Occupied","temperature":78.3,"humidity":0,"humidifySetting":0,"dehumidifySetting":0,"co2Setting":"","co2Level":"","setBy":"Schedule","frontKeypad":"On","runStatus":"Off","auxStatus":"Off","setback":"Off"},{"timestamp":"2025-08-31T09:16","system":"Auto","heatSetting":50,"coolSetting":95,"fan":"Auto","status":"Occupied","temperature":78.4,"humidity":0,"humidifySetting":0,"dehumidifySetting":0,"co2Setting":"","co2Level":"","setBy":"Schedule","frontKeypad":"On","runStatus":"Off","auxStatus":"Off","setback":"Off"},{"timestamp":"2025-08-31T09:21","system":"Auto","heatSetting":50,"coolSetting":95,"fan":"Auto","status":"Occupied","temperature":78.3,"humidity":0,"humidifySetting":0,"dehumidifySetting":0,"co2Setting":"","co2Level":"","setBy":"Schedule","frontKeypad":"On","runStatus":"Off","auxStatus":"Off","setback":"Off"},{"timestamp":"2025-08-31T09:27","system":"Auto","heatSetting":50,"coolSetting":95,"fan":"Auto","status":"Occupied","temperature":78.4,"humidity":0,"humidifySetting":0,"dehumidifySetting":0,"co2Setting":"","co2Level":"","setBy":"Schedule","frontKeypad":"On","runStatus":"Off","auxStatus":"Off","setback":"Off"},{"timestamp":"2025-08-31T09:32","system":"Auto","heatSetting":50,"coolSetting":95,"fan":"Auto","status":"Occupied","temperature":78.3,"humidity":0,"humidifySetting":0,"dehumidifySetting":0,"co2Setting":"","co2Level":"","setBy":"Schedule","frontKeypad":"On","runStatus":"Off","auxStatus":"Off","setback":"Off"},{"timestamp":"2025-08-31T09:37","system":"Auto","heatSetting":50,"coolSetting":95,"fan":"Auto","status":"Occupied","temperature":78.4,"humidity":0,"humidifySetting":0,"dehumidifySetting":0,"co2Setting":"","co2Level":"","setBy":"Schedule","frontKeypad":"On","runStatus":"Off","auxStatus":"Off","setback":"Off"},{"timestamp":"2025-08-31T10:05","system":"Auto","heatSetting":50,"coolSetting":95,"fan":"Auto","status":"Occupied","temperature":78.5,"humidity":0,"humidifySetting":0,"dehumidifySetting":0,"co2Setting":"","co2Level":"","setBy":"Schedule","frontKeypad":"On","runStatus":"Off","auxStatus":"Off","setback":"Off"},{"timestamp":"2025-08-31T10:37","system":"Auto","heatSetting":50,"coolSetting":95,"fan":"Auto","status":"Occupied","temperature":78.7,"humidity":0,"humidifySetting":0,"dehumidifySetting":0,"co2Setting":"","co2Level":"","setBy":"Schedule","frontKeypad":"On","runStatus":"Off","auxStatus":"Off","setback":"Off"},{"timestamp":"2025-08-31T10:55","system":"Auto","heatSetting":50,"coolSetting":95,"fan":"Auto","status":"Occupied","temperature":78.8,"humidity":0,"humidifySetting":0,"dehumidifySetting":0,"co2Setting":"","co2Level":"","setBy":"Schedule","frontKeypad":"On","runStatus":"Off","auxStatus":"Off","setback":"Off"},{"timestamp":"2025-08-31T11:14","system":"Auto","heatSetting":50,"coolSetting":95,"fan":"Auto","status":"Occupied","temperature":78.9,"humidity":0,"humidifySetting":0,"dehumidifySetting":0,"co2Setting":"","co2Level":"","setBy":"Schedule","frontKeypad":"On","runStatus":"Off","auxStatus":"Off","setback":"Off"},{"timestamp":"2025-08-31T11:29","system":"Auto","heatSetting":50,"coolSetting":95,"fan":"Auto","status":"Occupied","temperature":79,"humidity":0,"humidifySetting":0,"dehumidifySetting":0,"co2Setting":"","co2Level":"","setBy":"Schedule","frontKeypad":"On","runStatus":"Off","auxStatus":"Off","setback":"Off"},{"timestamp":"2025-08-31T11:43","system":"Auto","heatSetting":50,"coolSetting":95,"fan":"Auto","status":"Occupied","temperature":79.1,"humidity":0,"humidifySetting":0,"dehumidifySetting":0,"co2Setting":"","co2Level":"","setBy":"Schedule","frontKeypad":"On","runStatus":"Off","auxStatus":"Off","setback":"Off"},{"timestamp":"2025-08-31T11:57","system":"Auto","heatSetting":50,"coolSetting":95,"fan":"Auto","status":"Occupied","temperature":79.2,"humidity":0,"humidifySetting":0,"dehumidifySetting":0,"co2Setting":"","co2Level":"","setBy":"Schedule","frontKeypad":"On","runStatus":"Off","auxStatus":"Off","setback":"Off"},{"timestamp":"2025-08-31T12:10","system":"Auto","heatSetting":50,"coolSetting":95,"fan":"Auto","status":"Occupied","temperature":79.3,"humidity":0,"humidifySetting":0,"dehumidifySetting":0,"co2Setting":"","co2Level":"","setBy":"Schedule","frontKeypad":"On","runStatus":"Off","auxStatus":"Off","setback":"Off"},{"timestamp":"2025-08-31T12:19","system":"Auto","heatSetting":50,"coolSetting":95,"fan":"Auto","status":"Occupied","temperature":79.4,"humidity":0,"humidifySetting":0,"dehumidifySetting":0,"co2Setting":"","co2Level":"","setBy":"Schedule","frontKeypad":"On","runStatus":"Off","auxStatus":"Off","setback":"Off"},{"timestamp":"2025-08-31T12:31","system":"Auto","heatSetting":50,"coolSetting":95,"fan":"Auto","status":"Occupied","temperature":79.6,"humidity":0,"humidifySetting":0,"dehumidifySetting":0,"co2Setting":"","co2Level":"","setBy":"Schedule","frontKeypad":"On","runStatus":"Off","auxStatus":"Off","setback":"Off"},{"timestamp":"2025-08-31T12:39","system":"Auto","heatSetting":50,"coolSetting":95,"fan":"Auto","status":"Occupied","temperature":79.7,"humidity":0,"humidifySetting":0,"dehumidifySetting":0,"co2Setting":"","co2Level":"","setBy":"Schedule","frontKeypad":"On","runStatus":"Off","auxStatus":"Off","setback":"Off"},{"timestamp":"2025-08-31T12:48","system":"Auto","heatSetting":50,"coolSetting":95,"fan":"Auto","status":"Occupied","temperature":79.8,"humidity":0,"humidifySetting":0,"dehumidifySetting":0,"co2Setting":"","co2Level":"","setBy":"Schedule","frontKeypad":"On","runStatus":"Off","auxStatus":"Off","setback":"Off"},{"timestamp":"2025-08-31T13:07","system":"Auto","heatSetting":50,"coolSetting":95,"fan":"Auto","status":"Occupied","temperature":80,"humidity":0,"humidifySetting":0,"dehumidifySetting":0,"co2Setting":"","co2Level":"","setBy":"Schedule","frontKeypad":"On","runStatus":"Off","auxStatus":"Off","setback":"Off"},{"timestamp":"2025-08-31T13:14","system":"Auto","heatSetting":50,"coolSetting":95,"fan":"Auto","status":"Occupied","temperature":80.1,"humidity":0,"humidifySetting":0,"dehumidifySetting":0,"co2Setting":"","co2Level":"","setBy":"Schedule","frontKeypad":"On","runStatus":"Off","auxStatus":"Off","setback":"Off"},{"timestamp":"2025-08-31T13:25","system":"Auto","heatSetting":50,"coolSetting":95,"fan":"Auto","status":"Occupied","temperature":80.2,"humidity":0,"humidifySetting":0,"dehumidifySetting":0,"co2Setting":"","co2Level":"","setBy":"Schedule","frontKeypad":"On","runStatus":"Off","auxStatus":"Off","setback":"Off"},{"timestamp":"2025-08-31T13:30","system":"Auto","heatSetting":50,"coolSetting":95,"fan":"Auto","status":"Occupied","temperature":80.3,"humidity":0,"humidifySetting":0,"dehumidifySetting":0,"co2Setting":"","co2Level":"","setBy":"Schedule","frontKeypad":"On","runStatus":"Off","auxStatus":"Off","setback":"Off"},{"timestamp":"2025-08-31T13:44","system":"Auto","heatSetting":50,"coolSetting":95,"fan":"Auto","status":"Occupied","temperature":80.5,"humidity":0,"humidifySetting":0,"dehumidifySetting":0,"co2Setting":"","co2Level":"","setBy":"Schedule","frontKeypad":"On","runStatus":"Off","auxStatus":"Off","setback":"Off"},{"timestamp":"2025-08-31T13:51","system":"Auto","heatSetting":50,"coolSetting":95,"fan":"Auto","status":"Occupied","temperature":80.6,"humidity":0,"humidifySetting":0,"dehumidifySetting":0,"co2Setting":"","co2Level":"","setBy":"Schedule","frontKeypad":"On","runStatus":"Off","auxStatus":"Off","setback":"Off"},{"timestamp":"2025-08-31T14:01","system":"Auto","heatSetting":50,"coolSetting":95,"fan":"Auto","status":"Occupied","temperature":80.7,"humidity":0,"humidifySetting":0,"dehumidifySetting":0,"co2Setting":"","co2Level":"","setBy":"Schedule","frontKeypad":"On","runStatus":"Off","auxStatus":"Off","setback":"Off"},{"timestamp":"2025-08-31T14:10","system":"Auto","heatSetting":50,"coolSetting":95,"fan":"Auto","status":"Occupied","temperature":80.8,"humidity":0,"humidifySetting":0,"dehumidifySetting":0,"co2Setting":"","co2Level":"","setBy":"Schedule","frontKeypad":"On","runStatus":"Off","auxStatus":"Off","setback":"Off"},{"timestamp":"2025-08-31T14:19","system":"Auto","heatSetting":50,"coolSetting":95,"fan":"Auto","status":"Occupied","temperature":80.9,"humidity":0,"humidifySetting":0,"dehumidifySetting":0,"co2Setting":"","co2Level":"","setBy":"Schedule","frontKeypad":"On","runStatus":"Off","auxStatus":"Off","setback":"Off"},{"timestamp":"2025-08-31T14:28","system":"Auto","heatSetting":50,"coolSetting":95,"fan":"Auto","status":"Occupied","temperature":81,"humidity":0,"humidifySetting":0,"dehumidifySetting":0,"co2Setting":"","co2Level":"","setBy":"Schedule","frontKeypad":"On","runStatus":"Off","auxStatus":"Off","setback":"Off"},{"timestamp":"2025-08-31T14:38","system":"Auto","heatSetting":50,"coolSetting":95,"fan":"Auto","status":"Occupied","temperature":81.1,"humidity":0,"humidifySetting":0,"dehumidifySetting":0,"co2Setting":"","co2Level":"","setBy":"Schedule","frontKeypad":"On","runStatus":"Off","auxStatus":"Off","setback":"Off"},{"timestamp":"2025-08-31T14:47","system":"Auto","heatSetting":50,"coolSetting":95,"fan":"Auto","status":"Occupied","temperature":81.2,"humidity":0,"humidifySetting":0,"dehumidifySetting":0,"co2Setting":"","co2Level":"","setBy":"Schedule","frontKeypad":"On","runStatus":"Off","auxStatus":"Off","setback":"Off"},{"timestamp":"2025-08-31T14:58","system":"Auto","heatSetting":50,"coolSetting":95,"fan":"Auto","status":"Occupied","temperature":81.4,"humidity":0,"humidifySetting":0,"dehumidifySetting":0,"co2Setting":"","co2Level":"","setBy":"Schedule","frontKeypad":"On","runStatus":"Off","auxStatus":"Off","setback":"Off"},{"timestamp":"2025-08-31T15:04","system":"Auto","heatSetting":50,"coolSetting":95,"fan":"Auto","status":"Occupied","temperature":81.5,"humidity":0,"humidifySetting":0,"dehumidifySetting":0,"co2Setting":"","co2Level":"","setBy":"Schedule","frontKeypad":"On","runStatus":"Off","auxStatus":"Off","setback":"Off"},{"timestamp":"2025-08-31T15:12","system":"Auto","heatSetting":50,"coolSetting":95,"fan":"Auto","status":"Occupied","temperature":81.6,"humidity":0,"humidifySetting":0,"dehumidifySetting":0,"co2Setting":"","co2Level":"","setBy":"Schedule","frontKeypad":"On","runStatus":"Off","auxStatus":"Off","setback":"Off"},{"timestamp":"2025-08-31T15:25","system":"Auto","heatSetting":50,"coolSetting":95,"fan":"Auto","status":"Occupied","temperature":81.7,"humidity":0,"humidifySetting":0,"dehumidifySetting":0,"co2Setting":"","co2Level":"","setBy":"Schedule","frontKeypad":"On","runStatus":"Off","auxStatus":"Off","setback":"Off"},{"timestamp":"2025-08-31T15:35","system":"Auto","heatSetting":50,"coolSetting":95,"fan":"Auto","status":"Occupied","temperature":81.8,"humidity":0,"humidifySetting":0,"dehumidifySetting":0,"co2Setting":"","co2Level":"","setBy":"Schedule","frontKeypad":"On","runStatus":"Off","auxStatus":"Off","setback":"Off"},{"timestamp":"2025-08-31T15:46","system":"Auto","heatSetting":50,"coolSetting":95,"fan":"Auto","status":"Occupied","temperature":81.9,"humidity":0,"humidifySetting":0,"dehumidifySetting":0,"co2Setting":"","co2Level":"","setBy":"Schedule","frontKeypad":"On","runStatus":"Off","auxStatus":"Off","setback":"Off"},{"timestamp":"2025-08-31T15:55","system":"Auto","heatSetting":50,"coolSetting":95,"fan":"Auto","status":"Occupied","temperature":82,"humidity":0,"humidifySetting":0,"dehumidifySetting":0,"co2Setting":"","co2Level":"","setBy":"Schedule","frontKeypad":"On","runStatus":"Off","auxStatus":"Off","setback":"Off"},{"timestamp":"2025-08-31T16:07","system":"Auto","heatSetting":50,"coolSetting":95,"fan":"Auto","status":"Occupied","temperature":82.1,"humidity":0,"humidifySetting":0,"dehumidifySetting":0,"co2Setting":"","co2Level":"","setBy":"Schedule","frontKeypad":"On","runStatus":"Off","auxStatus":"Off","setback":"Off"},{"timestamp":"2025-08-31T16:17","system":"Auto","heatSetting":50,"coolSetting":95,"fan":"Auto","status":"Occupied","temperature":82.3,"humidity":0,"humidifySetting":0,"dehumidifySetting":0,"co2Setting":"","co2Level":"","setBy":"Schedule","frontKeypad":"On","runStatus":"Off","auxStatus":"Off","setback":"Off"},{"timestamp":"2025-08-31T16:25","system":"Auto","heatSetting":50,"coolSetting":95,"fan":"Auto","status":"Occupied","temperature":82.4,"humidity":0,"humidifySetting":0,"dehumidifySetting":0,"co2Setting":"","co2Level":"","setBy":"Schedule","frontKeypad":"On","runStatus":"Off","auxStatus":"Off","setback":"Off"},{"timestamp":"2025-08-31T16:36","system":"Auto","heatSetting":50,"coolSetting":95,"fan":"Auto","status":"Occupied","temperature":82.5,"humidity":0,"humidifySetting":0,"dehumidifySetting":0,"co2Setting":"","co2Level":"","setBy":"Schedule","frontKeypad":"On","runStatus":"Off","auxStatus":"Off","setback":"Off"},{"timestamp":"2025-08-31T16:48","system":"Auto","heatSetting":50,"coolSetting":95,"fan":"Auto","status":"Occupied","temperature":82.6,"humidity":0,"humidifySetting":0,"dehumidifySetting":0,"co2Setting":"","co2Level":"","setBy":"Schedule","frontKeypad":"On","runStatus":"Off","auxStatus":"Off","setback":"Off"},{"timestamp":"2025-08-31T17:02","system":"Auto","heatSetting":50,"coolSetting":95,"fan":"Auto","status":"Occupied","temperature":82.7,"humidity":0,"humidifySetting":0,"dehumidifySetting":0,"co2Setting":"","co2Level":"","setBy":"Schedule","frontKeypad":"On","runStatus":"Off","auxStatus":"Off","setback":"Off"},{"timestamp":"2025-08-31T17:12","system":"Auto","heatSetting":50,"coolSetting":95,"fan":"Auto","status":"Occupied","temperature":82.8,"humidity":0,"humidifySetting":0,"dehumidifySetting":0,"co2Setting":"","co2Level":"","setBy":"Schedule","frontKeypad":"On","runStatus":"Off","auxStatus":"Off","setback":"Off"},{"timestamp":"2025-08-31T17:28","system":"Auto","heatSetting":50,"coolSetting":95,"fan":"Auto","status":"Occupied","temperature":82.9,"humidity":0,"humidifySetting":0,"dehumidifySetting":0,"co2Setting":"","co2Level":"","setBy":"Schedule","frontKeypad":"On","runStatus":"Off","auxStatus":"Off","setback":"Off"},{"timestamp":"2025-08-31T17:57","system":"Auto","heatSetting":50,"coolSetting":95,"fan":"Auto","status":"Occupied","temperature":83,"humidity":0,"humidifySetting":0,"dehumidifySetting":0,"co2Setting":"","co2Level":"","setBy":"Schedule","frontKeypad":"On","runStatus":"Off","auxStatus":"Off","setback":"Off"},{"timestamp":"2025-08-31T18:00","system":"Auto","heatSetting":50,"coolSetting":95,"fan":"Auto","status":"Occupied","temperature":82.9,"humidity":0,"humidifySetting":0,"dehumidifySetting":0,"co2Setting":"","co2Level":"","setBy":"Schedule","frontKeypad":"On","runStatus":"Off","auxStatus":"Off","setback":"Off"},{"timestamp":"2025-08-31T18:02","system":"Auto","heatSetting":50,"coolSetting":95,"fan":"Auto","status":"Occupied","temperature":83,"humidity":0,"humidifySetting":0,"dehumidifySetting":0,"co2Setting":"","co2Level":"","setBy":"Schedule","frontKeypad":"On","runStatus":"Off","auxStatus":"Off","setback":"Off"},{"timestamp":"2025-08-31T18:06","system":"Auto","heatSetting":50,"coolSetting":95,"fan":"Auto","status":"Occupied","temperature":82.9,"humidity":0,"humidifySetting":0,"dehumidifySetting":0,"co2Setting":"","co2Level":"","setBy":"Schedule","frontKeypad":"On","runStatus":"Off","auxStatus":"Off","setback":"Off"},{"timestamp":"2025-08-31T18:08","system":"Auto","heatSetting":50,"coolSetting":95,"fan":"Auto","status":"Occupied","temperature":83,"humidity":0,"humidifySetting":0,"dehumidifySetting":0,"co2Setting":"","co2Level":"","setBy":"Schedule","frontKeypad":"On","runStatus":"Off","auxStatus":"Off","setback":"Off"},{"timestamp":"2025-08-31T18:16","system":"Auto","heatSetting":50,"coolSetting":95,"fan":"Auto","status":"Occupied","temperature":82.9,"humidity":0,"humidifySetting":0,"dehumidifySetting":0,"co2Setting":"","co2Level":"","setBy":"Schedule","frontKeypad":"On","runStatus":"Off","auxStatus":"Off","setback":"Off"},{"timestamp":"2025-08-31T18:26","system":"Auto","heatSetting":50,"coolSetting":95,"fan":"Auto","status":"Occupied","temperature":83,"humidity":0,"humidifySetting":0,"dehumidifySetting":0,"co2Setting":"","co2Level":"","setBy":"Schedule","frontKeypad":"On","runStatus":"Off","auxStatus":"Off","setback":"Off"},{"timestamp":"2025-08-31T18:28","system":"Auto","heatSetting":50,"coolSetting":95,"fan":"Auto","status":"Occupied","temperature":82.9,"humidity":0,"humidifySetting":0,"dehumidifySetting":0,"co2Setting":"","co2Level":"","setBy":"Schedule","frontKeypad":"On","runStatus":"Off","auxStatus":"Off","setback":"Off"},{"timestamp":"2025-08-31T18:30","system":"Auto","heatSetting":50,"coolSetting":95,"fan":"Auto","status":"Occupied","temperature":83,"humidity":0,"humidifySetting":0,"dehumidifySetting":0,"co2Setting":"","co2Level":"","setBy":"Schedule","frontKeypad":"On","runStatus":"Off","auxStatus":"Off","setback":"Off"},{"timestamp":"2025-08-31T18:32","system":"Auto","heatSetting":50,"coolSetting":95,"fan":"Auto","status":"Occupied","temperature":82.9,"humidity":0,"humidifySetting":0,"dehumidifySetting":0,"co2Setting":"","co2Level":"","setBy":"Schedule","frontKeypad":"On","runStatus":"Off","auxStatus":"Off","setback":"Off"},{"timestamp":"2025-08-31T19:04","system":"Auto","heatSetting":50,"coolSetting":95,"fan":"Auto","status":"Occupied","temperature":82.8,"humidity":0,"humidifySetting":0,"dehumidifySetting":0,"co2Setting":"","co2Level":"","setBy":"Schedule","frontKeypad":"On","runStatus":"Off","auxStatus":"Off","setback":"Off"},{"timestamp":"2025-08-31T19:23","system":"Auto","heatSetting":50,"coolSetting":95,"fan":"Auto","status":"Occupied","temperature":82.7,"humidity":0,"humidifySetting":0,"dehumidifySetting":0,"co2Setting":"","co2Level":"","setBy":"Schedule","frontKeypad":"On","runStatus":"Off","auxStatus":"Off","setback":"Off"},{"timestamp":"2025-08-31T19:42","system":"Auto","heatSetting":50,"coolSetting":95,"fan":"Auto","status":"Occupied","temperature":82.6,"humidity":0,"humidifySetting":0,"dehumidifySetting":0,"co2Setting":"","co2Level":"","setBy":"Schedule","frontKeypad":"On","runStatus":"Off","auxStatus":"Off","setback":"Off"},{"timestamp":"2025-08-31T19:57","system":"Auto","heatSetting":50,"coolSetting":95,"fan":"Auto","status":"Occupied","temperature":82.5,"humidity":0,"humidifySetting":0,"dehumidifySetting":0,"co2Setting":"","co2Level":"","setBy":"Schedule","frontKeypad":"On","runStatus":"Off","auxStatus":"Off","setback":"Off"},{"timestamp":"2025-08-31T20:12","system":"Auto","heatSetting":50,"coolSetting":95,"fan":"Auto","status":"Occupied","temperature":82.4,"humidity":0,"humidifySetting":0,"dehumidifySetting":0,"co2Setting":"","co2Level":"","setBy":"Schedule","frontKeypad":"On","runStatus":"Off","auxStatus":"Off","setback":"Off"},{"timestamp":"2025-08-31T20:25","system":"Auto","heatSetting":50,"coolSetting":95,"fan":"Auto","status":"Occupied","temperature":82.3,"humidity":0,"humidifySetting":0,"dehumidifySetting":0,"co2Setting":"","co2Level":"","setBy":"Schedule","frontKeypad":"On","runStatus":"Off","auxStatus":"Off","setback":"Off"},{"timestamp":"2025-08-31T20:38","system":"Auto","heatSetting":50,"coolSetting":95,"fan":"Auto","status":"Occupied","temperature":82.1,"humidity":0,"humidifySetting":0,"dehumidifySetting":0,"co2Setting":"","co2Level":"","setBy":"Schedule","frontKeypad":"On","runStatus":"Off","auxStatus":"Off","setback":"Off"},{"timestamp":"2025-08-31T20:53","system":"Auto","heatSetting":50,"coolSetting":95,"fan":"Auto","status":"Occupied","temperature":82,"humidity":0,"humidifySetting":0,"dehumidifySetting":0,"co2Setting":"","co2Level":"","setBy":"Schedule","frontKeypad":"On","runStatus":"Off","auxStatus":"Off","setback":"Off"},{"timestamp":"2025-08-31T21:06","system":"Auto","heatSetting":50,"coolSetting":95,"fan":"Auto","status":"Occupied","temperature":81.9,"humidity":0,"humidifySetting":0,"dehumidifySetting":0,"co2Setting":"","co2Level":"","setBy":"Schedule","frontKeypad":"On","runStatus":"Off","auxStatus":"Off","setback":"Off"},{"timestamp":"2025-08-31T21:21","system":"Auto","heatSetting":50,"coolSetting":95,"fan":"Auto","status":"Occupied","temperature":81.8,"humidity":0,"humidifySetting":0,"dehumidifySetting":0,"co2Setting":"","co2Level":"","setBy":"Schedule","frontKeypad":"On","runStatus":"Off","auxStatus":"Off","setback":"Off"},{"timestamp":"2025-08-31T21:32","system":"Auto","heatSetting":50,"coolSetting":95,"fan":"Auto","status":"Occupied","temperature":81.7,"humidity":0,"humidifySetting":0,"dehumidifySetting":0,"co2Setting":"","co2Level":"","setBy":"Schedule","frontKeypad":"On","runStatus":"Off","auxStatus":"Off","setback":"Off"},{"timestamp":"2025-08-31T21:44","system":"Auto","heatSetting":50,"coolSetting":95,"fan":"Auto","status":"Occupied","temperature":81.6,"humidity":0,"humidifySetting":0,"dehumidifySetting":0,"co2Setting":"","co2Level":"","setBy":"Schedule","frontKeypad":"On","runStatus":"Off","auxStatus":"Off","setback":"Off"},{"timestamp":"2025-08-31T21:59","system":"Auto","heatSetting":50,"coolSetting":95,"fan":"Auto","status":"Occupied","temperature":81.5,"humidity":0,"humidifySetting":0,"dehumidifySetting":0,"co2Setting":"","co2Level":"","setBy":"Schedule","frontKeypad":"On","runStatus":"Off","auxStatus":"Off","setback":"Off"},{"timestamp":"2025-08-31T22:14","system":"Auto","heatSetting":50,"coolSetting":95,"fan":"Auto","status":"Occupied","temperature":81.4,"humidity":0,"humidifySetting":0,"dehumidifySetting":0,"co2Setting":"","co2Level":"","setBy":"Schedule","frontKeypad":"On","runStatus":"Off","auxStatus":"Off","setback":"Off"},{"timestamp":"2025-08-31T22:22","system":"Auto","heatSetting":50,"coolSetting":95,"fan":"Auto","status":"Occupied","temperature":81.2,"humidity":0,"humidifySetting":0,"dehumidifySetting":0,"co2Setting":"","co2Level":"","setBy":"Schedule","frontKeypad":"On","runStatus":"Off","auxStatus":"Off","setback":"Off"},{"timestamp":"2025-08-31T22:34","system":"Auto","heatSetting":50,"coolSetting":95,"fan":"Auto","status":"Occupied","temperature":81.1,"humidity":0,"humidifySetting":0,"dehumidifySetting":0,"co2Setting":"","co2Level":"","setBy":"Schedule","frontKeypad":"On","runStatus":"Off","auxStatus":"Off","setback":"Off"},{"timestamp":"2025-08-31T22:49","system":"Auto","heatSetting":50,"coolSetting":95,"fan":"Auto","status":"Occupied","temperature":81,"humidity":0,"humidifySetting":0,"dehumidifySetting":0,"co2Setting":"","co2Level":"","setBy":"Schedule","frontKeypad":"On","runStatus":"Off","auxStatus":"Off","setback":"Off"},{"timestamp":"2025-08-31T22:59","system":"Auto","heatSetting":50,"coolSetting":95,"fan":"Auto","status":"Occupied","temperature":81,"humidity":0,"humidifySetting":0,"dehumidifySetting":0,"co2Setting":"","co2Level":"","setBy":"Schedule","frontKeypad":"On","runStatus":"Off","auxStatus":"Off","setback":"Off"},{"timestamp":"2025-08-31T23:01","system":"Auto","heatSetting":50,"coolSetting":95,"fan":"Auto","status":"Occupied","temperature":80.9,"humidity":0,"humidifySetting":0,"dehumidifySetting":0,"co2Setting":"","co2Level":"","setBy":"Schedule","frontKeypad":"On","runStatus":"Off","auxStatus":"Off","setback":"Off"},{"timestamp":"2025-08-31T23:04","system":"Auto","heatSetting":50,"coolSetting":95,"fan":"Auto","status":"Occupied","temperature":81,"humidity":0,"humidifySetting":0,"dehumidifySetting":0,"co2Setting":"","co2Level":"","setBy":"Schedule","frontKeypad":"On","runStatus":"Off","auxStatus":"Off","setback":"Off"},{"timestamp":"2025-08-31T23:06","system":"Auto","heatSetting":50,"coolSetting":95,"fan":"Auto","status":"Occupied","temperature":80.9,"humidity":0,"humidifySetting":0,"dehumidifySetting":0,"co2Setting":"","co2Level":"","setBy":"Schedule","frontKeypad":"On","runStatus":"Off","auxStatus":"Off","setback":"Off"},{"timestamp":"2025-08-31T23:16","system":"Auto","heatSetting":50,"coolSetting":95,"fan":"Auto","status":"Occupied","temperature":80.8,"humidity":0,"humidifySetting":0,"dehumidifySetting":0,"co2Setting":"","co2Level":"","setBy":"Schedule","frontKeypad":"On","runStatus":"Off","auxStatus":"Off","setback":"Off"},{"timestamp":"2025-08-31T23:30","system":"Auto","heatSetting":50,"coolSetting":95,"fan":"Auto","status":"Occupied","temperature":80.7,"humidity":0,"humidifySetting":0,"dehumidifySetting":0,"co2Setting":"","co2Level":"","setBy":"Schedule","frontKeypad":"On","runStatus":"Off","auxStatus":"Off","setback":"Off"},{"timestamp":"2025-08-31T23:42","system":"Auto","heatSetting":50,"coolSetting":95,"fan":"Auto","status":"Occupied","temperature":80.6,"humidity":0,"humidifySetting":0,"dehumidifySetting":0,"co2Setting":"","co2Level":"","setBy":"Schedule","frontKeypad":"On","runStatus":"Off","auxStatus":"Off","setback":"Off"}]}