{"name":"JH-410A","groupName":"400s","serialNo":"8A3-USPH","History":[{"timestamp":"2025-08-30T00:15","system":"Auto","heatSetting":60,"coolSetting":85,"fan":"Auto","status":"Occupied","temperature":74.7,"humidity":0,"humidifySetting":0,"dehumidifySetting":0,"co2Setting":"","co2Level":"0","setBy":"Schedule","frontKeypad":"On","runStatus":"Off","auxStatus":"Off","setback":"Off"},{"timestamp":"2025-08-30T00:57","system":"Auto","heatSetting":60,"coolSetting":85,"fan":"Auto","status":"Occupied","temperature":74.8,"humidity":0,"humidifySetting":0,"dehumidifySetting":0,"co2Setting":"","co2Level":"0","setBy":"Schedule","frontKeypad":"On","runStatus":"Off","auxStatus":"Off","setback":"Off"},{"timestamp":"2025-08-30T01:05","system":"Auto","heatSetting":60,"coolSetting":85,"fan":"Auto","status":"Occupied","temperature":74.7,"humidity":0,"humidifySetting":0,"dehumidifySetting":0,"co2Setting":"","co2Level":"0","setBy":"Schedule","frontKeypad":"On","runStatus":"Off","auxStatus":"Off","setback":"Off"},{"timestamp":"2025-08-30T01:09","system":"Auto","heatSetting":60,"coolSetting":85,"fan":"Auto","status":"Occupied","temperature":74.8,"humidity":0,"humidifySetting":0,"dehumidifySetting":0,"co2Setting":"","co2Level":"0","setBy":"Schedule","frontKeypad":"On","runStatus":"Off","auxStatus":"Off","setback":"Off"},{"timestamp":"2025-08-30T01:41","system":"Auto","heatSetting":60,"coolSetting":85,"fan":"Auto","status":"Occupied","temperature":74.9,"humidity":0,"humidifySetting":0,"dehumidifySetting":0,"co2Setting":"","co2Level":"0","setBy":"Schedule","frontKeypad":"On","runStatus":"Off","auxStatus":"Off","setback":"Off"},{"timestamp":"2025-08-30T02:00","system":"Auto","heatSetting":60,"coolSetting":85,"fan":"Auto","status":"Occupied","temperature":74.9,"humidity":0,"humidifySetting":0,"dehumidifySetting":0,"co2Setting":"","co2Level":"0","setBy":"Schedule","frontKeypad":"On","runStatus":"Off","auxStatus":"Off","setback":"Off"},{"timestamp":"2025-08-30T02:37","system":"Auto","heatSetting":60,"coolSetting":85,"fan":"Auto","status":"Occupied","temperature":75.1,"humidity":0,"humidifySetting":0,"dehumidifySetting":0,"co2Setting":"","co2Level":"0","setBy":"Schedule","frontKeypad":"On","runStatus":"Off","auxStatus":"Off","setback":"Off"},{"timestamp":"2025-08-30T02:39","system":"Auto","heatSetting":60,"coolSetting":85,"fan":"Auto","status":"Occupied","temperature":74.9,"humidity":0,"humidifySetting":0,"dehumidifySetting":0,"co2Setting":"","co2Level":"0","setBy":"Schedule","frontKeypad":"On","runStatus":"Off","auxStatus":"Off","setback":"Off"},{"timestamp":"2025-08-30T02:44","system":"Auto","heatSetting":60,"coolSetting":85,"fan":"Auto","status":"Occupied","temperature":75.1,"humidity":0,"humidifySetting":0,"dehumidifySetting":0,"co2Setting":"","co2Level":"0","setBy":"Schedule","frontKeypad":"On","runStatus":"Off","auxStatus":"Off","setback":"Off"},{"timestamp":"2025-08-30T02:46","system":"Auto","heatSetting":60,"coolSetting":85,"fan":"Auto","status":"Occupied","temperature":74.9,"humidity":0,"humidifySetting":0,"dehumidifySetting":0,"co2Setting":"","co2Level":"0","setBy":"Schedule","frontKeypad":"On","runStatus":"Off","auxStatus":"Off","setback":"Off"},{"timestamp":"2025-08-30T02:48","system":"Auto","heatSetting":60,"coolSetting":85,"fan":"Auto","status":"Occupied","temperature":75.1,"humidity":0,"humidifySetting":0,"dehumidifySetting":0,"co2Setting":"","co2Level":"","setBy":"Schedule","frontKeypad":"On","runStatus":"Off","auxStatus":"Off","setback":"Off"},{"timestamp":"2025-08-30T02:50","system":"Auto","heatSetting":60,"coolSetting":85,"fan":"Auto","status":"Occupied","temperature":74.9,"humidity":0,"humidifySetting":0,"dehumidifySetting":0,"co2Setting":"","co2Level":"","setBy":"Schedule","frontKeypad":"On","runStatus":"Off","auxStatus":"Off","setback":"Off"},{"timestamp":"2025-08-30T02:52","system":"Auto","heatSetting":60,"coolSetting":85,"fan":"Auto","status":"Occupied","temperature":75.1,"humidity":0,"humidifySetting":0,"dehumidifySetting":0,"co2Setting":"","co2Level":"","setBy":"Schedule","frontKeypad":"On","runStatus":"Off","auxStatus":"Off","setback":"Off"},{"timestamp":"2025-08-30T02:56","system":"Auto","heatSetting":60,"coolSetting":85,"fan":"Auto","status":"Occupied","temperature":74.9,"humidity":0,"humidifySetting":0,"dehumidifySetting":0,"co2Setting":"","co2Level":"","setBy":"Schedule","frontKeypad":"On","runStatus":"Off","auxStatus":"Off","setback":"Off"},{"timestamp":"2025-08-30T02:58","system":"Auto","heatSetting":60,"coolSetting":85,"fan":"Auto","status":"Occupied","temperature":75.1,"humidity":0,"humidifySetting":0,"dehumidifySetting":0,"co2Setting":"","co2Level":"","setBy":"Schedule","frontKeypad":"On","runStatus":"Off","auxStatus":"Off","setback":"Off"},{"timestamp":"2025-08-30T03:01","system":"Auto","heatSetting":60,"coolSetting":85,"fan":"Auto","status":"Occupied","temperature":74.9,"humidity":0,"humidifySetting":0,"dehumidifySetting":0,"co2Setting":"","co2Level":"","setBy":"Schedule","frontKeypad":"On","runStatus":"Off","auxStatus":"Off","setback":"Off"},{"timestamp":"2025-08-30T03:03","system":"Auto","heatSetting":60,"coolSetting":85,"fan":"Auto","status":"Occupied","temperature":75.1,"humidity":0,"humidifySetting":0,"dehumidifySetting":0,"co2Setting":"","co2Level":"","setBy":"Schedule","frontKeypad":"On","runStatus":"Off","auxStatus":"Off","setback":"Off"},{"timestamp":"2025-08-30T04:00","system":"Auto","heatSetting":60,"coolSetting":85,"fan":"Auto","status":"Occupied","temperature":75.1,"humidity":0,"humidifySetting":0,"dehumidifySetting":0,"co2Setting":"","co2Level":"","setBy":"Schedule","frontKeypad":"On","runStatus":"Off","auxStatus":"Off","setback":"Off"},{"timestamp":"2025-08-30T04:10","system":"Auto","heatSetting":60,"coolSetting":85,"fan":"Auto","status":"Occupied","temperature":75.2,"humidity":0,"humidifySetting":0,"dehumidifySetting":0,"co2Setting":"","co2Level":"","setBy":"Schedule","frontKeypad":"On","runStatus":"Off","auxStatus":"Off","setback":"Off"},{"timestamp":"2025-08-30T04:17","system":"Auto","heatSetting":60,"coolSetting":85,"fan":"Auto","status":"Occupied","temperature":75.1,"humidity":0,"humidifySetting":0,"dehumidifySetting":0,"co2Setting":"","co2Level":"","setBy":"Schedule","frontKeypad":"On","runStatus":"Off","auxStatus":"Off","setback":"Off"},{"timestamp":"2025-08-30T04:24","system":"Auto","heatSetting":60,"coolSetting":85,"fan":"Auto","status":"Occupied","temperature":75.2,"humidity":0,"humidifySetting":0,"dehumidifySetting":0,"co2Setting":"","co2Level":"","setBy":"Schedule","frontKeypad":"On","runStatus":"Off","auxStatus":"Off","setback":"Off"},{"timestamp":"2025-08-30T04:30","system":"Auto","heatSetting":60,"coolSetting":85,"fan":"Auto","status":"Occupied","temperature":75.1,"humidity":0,"humidifySetting":0,"dehumidifySetting":0,"co2Setting":"","co2Level":"","setBy":"Schedule","frontKeypad":"On","runStatus":"Off","auxStatus":"Off","setback":"Off"},{"timestamp":"2025-08-30T04:35","system":"Auto","heatSetting":60,"coolSetting":85,"fan":"Auto","status":"Occupied","temperature":75.2,"humidity":0,"humidifySetting":0,"dehumidifySetting":0,"co2Setting":"","co2Level":"","setBy":"Schedule","frontKeypad":"On","runStatus":"Off","auxStatus":"Off","setback":"Off"},{"timestamp":"2025-08-30T04:41","system":"Auto","heatSetting":60,"coolSetting":85,"fan":"Auto","status":"Occupied","temperature":75.1,"humidity":0,"humidifySetting":0,"dehumidifySetting":0,"co2Setting":"","co2Level":"","setBy":"Schedule","frontKeypad":"On","runStatus":"Off","auxStatus":"Off","setback":"Off"},{"timestamp":"2025-08-30T04:46","system":"Auto","heatSetting":60,"coolSetting":85,"fan":"Auto","status":"Occupied","temperature":75.2,"humidity":0,"humidifySetting":0,"dehumidifySetting":0,"co2Setting":"","co2Level":"","setBy":"Schedule","frontKeypad":"On","runStatus":"Off","auxStatus":"Off","setback":"Off"},{"timestamp":"2025-08-30T05:17","system":"Auto","heatSetting":60,"coolSetting":85,"fan":"Auto","status":"Occupied","temperature":75.1,"humidity":0,"humidifySetting":0,"dehumidifySetting":0,"co2Setting":"","co2Level":"","setBy":"Schedule","frontKeypad":"On","runStatus":"Off","auxStatus":"Off","setback":"Off"},{"timestamp":"2025-08-30T05:22","system":"Auto","heatSetting":60,"coolSetting":85,"fan":"Auto","status":"Occupied","temperature":75.2,"humidity":0,"humidifySetting":0,"dehumidifySetting":0,"co2Setting":"","co2Level":"","setBy":"Schedule","frontKeypad":"On","runStatus":"Off","auxStatus":"Off","setback":"Off"},{"timestamp":"2025-08-30T05:30","system":"Auto","heatSetting":60,"coolSetting":85,"fan":"Auto","status":"Occupied","temperature":75.1,"humidity":0,"humidifySetting":0,"dehumidifySetting":0,"co2Setting":"","co2Level":"","setBy":"Schedule","frontKeypad":"On","runStatus":"Off","auxStatus":"Off","setback":"Off"},{"timestamp":"2025-08-30T05:35","system":"Auto","heatSetting":60,"coolSetting":85,"fan":"Auto","status":"Occupied","temperature":75.2,"humidity":0,"humidifySetting":0,"dehumidifySetting":0,"co2Setting":"","co2Level":"","setBy":"Schedule","frontKeypad":"On","runStatus":"Off","auxStatus":"Off","setback":"Off"},{"timestamp":"2025-08-30T05:40","system":"Auto","heatSetting":60,"coolSetting":85,"fan":"Auto","status":"Occupied","temperature":75.1,"humidity":0,"humidifySetting":0,"dehumidifySetting":0,"co2Setting":"","co2Level":"","setBy":"Schedule","frontKeypad":"On","runStatus":"Off","auxStatus":"Off","setback":"Off"},{"timestamp":"2025-08-30T05:45","system":"Auto","heatSetting":60,"coolSetting":85,"fan":"Auto","status":"Occupied","temperature":75.2,"humidity":0,"humidifySetting":0,"dehumidifySetting":0,"co2Setting":"","co2Level":"","setBy":"Schedule","frontKeypad":"On","runStatus":"Off","auxStatus":"Off","setback":"Off"},{"timestamp":"2025-08-30T05:51","system":"Auto","heatSetting":60,"coolSetting":85,"fan":"Auto","status":"Occupied","temperature":75.1,"humidity":0,"humidifySetting":0,"dehumidifySetting":0,"co2Setting":"","co2Level":"","setBy":"Schedule","frontKeypad":"On","runStatus":"Off","auxStatus":"Off","setback":"Off"},{"timestamp":"2025-08-30T05:56","system":"Auto","heatSetting":60,"coolSetting":85,"fan":"Auto","status":"Occupied","temperature":75.2,"humidity":0,"humidifySetting":0,"dehumidifySetting":0,"co2Setting":"","co2Level":"","setBy":"Schedule","frontKeypad":"On","runStatus":"Off","auxStatus":"Off","setback":"Off"},{"timestamp":"2025-08-30T06:56","system":"Auto","heatSetting":60,"coolSetting":85,"fan":"Auto","status":"Occupied","temperature":75.2,"humidity":0,"humidifySetting":0,"dehumidifySetting":0,"co2Setting":"","co2Level":"","setBy":"Schedule","frontKeypad":"On","runStatus":"Off","auxStatus":"Off","setback":"Off"},{"timestamp":"2025-08-30T07:22","system":"Auto","heatSetting":60,"coolSetting":85,"fan":"Auto","status":"Occupied","temperature":75.1,"humidity":0,"humidifySetting":0,"dehumidifySetting":0,"co2Setting":"","co2Level":"","setBy":"Schedule","frontKeypad":"On","runStatus":"Off","auxStatus":"Off","setback":"Off"},{"timestamp":"2025-08-30T07:27","system":"Auto","heatSetting":60,"coolSetting":85,"fan":"Auto","status":"Occupied","temperature":75.2,"humidity":0,"humidifySetting":0,"dehumidifySetting":0,"co2Setting":"","co2Level":"","setBy":"Schedule","frontKeypad":"On","runStatus":"Off","auxStatus":"Off","setback":"Off"},{"timestamp":"2025-08-30T08:00","system":"Auto","heatSetting":60,"coolSetting":85,"fan":"Auto","status":"Occupied","temperature":75.2,"humidity":0,"humidifySetting":0,"dehumidifySetting":0,"co2Setting":"","co2Level":"","setBy":"Schedule","frontKeypad":"On","runStatus":"Off","auxStatus":"Off","setback":"Off"},{"timestamp":"2025-08-30T08:13","system":"Auto","heatSetting":60,"coolSetting":85,"fan":"Auto","status":"Occupied","temperature":75.3,"humidity":0,"humidifySetting":0,"dehumidifySetting":0,"co2Setting":"","co2Level":"","setBy":"Schedule","frontKeypad":"On","runStatus":"Off","auxStatus":"Off","setback":"Off"},{"timestamp":"2025-08-30T08:18","system":"Auto","heatSetting":60,"coolSetting":85,"fan":"Auto","status":"Occupied","temperature":75.2,"humidity":0,"humidifySetting":0,"dehumidifySetting":0,"co2Setting":"","co2Level":"","setBy":"Schedule","frontKeypad":"On","runStatus":"Off","auxStatus":"Off","setback":"Off"},{"timestamp":"2025-08-30T08:24","system":"Auto","heatSetting":60,"coolSetting":85,"fan":"Auto","status":"Occupied","temperature":75.3,"humidity":0,"humidifySetting":0,"dehumidifySetting":0,"co2Setting":"","co2Level":"","setBy":"Schedule","frontKeypad":"On","runStatus":"Off","auxStatus":"Off","setback":"Off"},{"timestamp":"2025-08-30T09:04","system":"Auto","heatSetting":60,"coolSetting":85,"fan":"Auto","status":"Occupied","temperature":75.4,"humidity":0,"humidifySetting":0,"dehumidifySetting":0,"co2Setting":"","co2Level":"","setBy":"Schedule","frontKeypad":"On","runStatus":"Off","auxStatus":"Off","setback":"Off"},{"timestamp":"2025-08-30T09:29","system":"Auto","heatSetting":60,"coolSetting":85,"fan":"Auto","status":"Occupied","temperature":75.5,"humidity":0,"humidifySetting":0,"dehumidifySetting":0,"co2Setting":"","co2Level":"","setBy":"Schedule","frontKeypad":"On","runStatus":"Off","auxStatus":"Off","setback":"Off"},{"timestamp":"2025-08-30T09:45","system":"Auto","heatSetting":60,"coolSetting":85,"fan":"Auto","status":"Occupied","temperature":75.6,"humidity":0,"humidifySetting":0,"dehumidifySetting":0,"co2Setting":"","co2Level":"","setBy":"Schedule","frontKeypad":"On","runStatus":"Off","auxStatus":"Off","setback":"Off"},{"timestamp":"2025-08-30T09:53","system":"Auto","heatSetting":60,"coolSetting":85,"fan":"Auto","status":"Occupied","temperature":75.5,"humidity":0,"humidifySetting":0,"dehumidifySetting":0,"co2Setting":"","co2Level":"","setBy":"Schedule","frontKeypad":"On","runStatus":"Off","auxStatus":"Off","setback":"Off"},{"timestamp":"2025-08-30T09:58","system":"Auto","heatSetting":60,"coolSetting":85,"fan":"Auto","status":"Occupied","temperature":75.6,"humidity":0,"humidifySetting":0,"dehumidifySetting":0,"co2Setting":"","co2Level":"","setBy":"Schedule","frontKeypad":"On","runStatus":"Off","auxStatus":"Off","setback":"Off"},{"timestamp":"2025-08-30T10:07","system":"Auto","heatSetting":60,"coolSetting":85,"fan":"Auto","status":"Occupied","temperature":75.7,"humidity":0,"humidifySetting":0,"dehumidifySetting":0,"co2Setting":"","co2Level":"","setBy":"Schedule","frontKeypad":"On","runStatus":"Off","auxStatus":"Off","setback":"Off"},{"timestamp":"2025-08-30T10:27","system":"Auto","heatSetting":60,"coolSetting":85,"fan":"Auto","status":"Occupied","temperature":75.8,"humidity":0,"humidifySetting":0,"dehumidifySetting":0,"co2Setting":"","co2Level":"","setBy":"Schedule","frontKeypad":"On","runStatus":"Off","auxStatus":"Off","setback":"Off"},{"timestamp":"2025-08-30T10:40","system":"Auto","heatSetting":60,"coolSetting":85,"fan":"Auto","status":"Occupied","temperature":76,"humidity":0,"humidifySetting":0,"dehumidifySetting":0,"co2Setting":"","co2Level":"","setBy":"Schedule","frontKeypad":"On","runStatus":"Off","auxStatus":"Off","setback":"Off"},{"timestamp":"2025-08-30T11:02","system":"Auto","heatSetting":60,"coolSetting":85,"fan":"Auto","status":"Occupied","temperature":76.1,"humidity":0,"humidifySetting":0,"dehumidifySetting":0,"co2Setting":"","co2Level":"","setBy":"Schedule","frontKeypad":"On","runStatus":"Off","auxStatus":"Off","setback":"Off"},{"timestamp":"2025-08-30T11:16","system":"Auto","heatSetting":60,"coolSetting":85,"fan":"Auto","status":"Occupied","temperature":76.2,"humidity":0,"humidifySetting":0,"dehumidifySetting":0,"co2Setting":"","co2Level":"","setBy":"Schedule","frontKeypad":"On","runStatus":"Off","auxStatus":"Off","setback":"Off"},{"timestamp":"2025-08-30T11:30","system":"Auto","heatSetting":60,"coolSetting":85,"fan":"Auto","status":"Occupied","temperature":76.3,"humidity":0,"humidifySetting":0,"dehumidifySetting":0,"co2Setting":"","co2Level":"","setBy":"Schedule","frontKeypad":"On","runStatus":"Off","auxStatus":"Off","setback":"Off"},{"timestamp":"2025-08-30T11:42","system":"Auto","heatSetting":60,"coolSetting":85,"fan":"Auto","status":"Occupied","temperature":76.4,"humidity":0,"humidifySetting":0,"dehumidifySetting":0,"co2Setting":"","co2Level":"","setBy":"Schedule","frontKeypad":"On","runStatus":"Off","auxStatus":"Off","setback":"Off"},{"timestamp":"2025-08-30T11:52","system":"Auto","heatSetting":60,"coolSetting":85,"fan":"Auto","status":"Occupied","temperature":76.5,"humidity":0,"humidifySetting":0,"dehumidifySetting":0,"co2Setting":"","co2Level":"","setBy":"Schedule","frontKeypad":"On","runStatus":"Off","auxStatus":"Off","setback":"Off"},{"timestamp":"2025-08-30T12:00","system":"Auto","heatSetting":60,"coolSetting":85,"fan":"Auto","status":"Occupied","temperature":76.5,"humidity":0,"humidifySetting":0,"dehumidifySetting":0,"co2Setting":"","co2Level":"","setBy":"Schedule","frontKeypad":"On","runStatus":"Off","auxStatus":"Off","setback":"Off"},{"timestamp":"2025-08-30T12:04","system":"Auto","heatSetting":60,"coolSetting":85,"fan":"Auto","status":"Occupied","temperature":76.6,"humidity":0,"humidifySetting":0,"dehumidifySetting":0,"co2Setting":"","co2Level":"","setBy":"Schedule","frontKeypad":"On","runStatus":"Off","auxStatus":"Off","setback":"Off"},{"timestamp":"2025-08-30T12:12","system":"Auto","heatSetting":60,"coolSetting":85,"fan":"Auto","status":"Occupied","temperature":76.7,"humidity":0,"humidifySetting":0,"dehumidifySetting":0,"co2Setting":"","co2Level":"","setBy":"Schedule","frontKeypad":"On","runStatus":"Off","auxStatus":"Off","setback":"Off"},{"timestamp":"2025-08-30T12:20","system":"Auto","heatSetting":60,"coolSetting":85,"fan":"Auto","status":"Occupied","temperature":76.9,"humidity":0,"humidifySetting":0,"dehumidifySetting":0,"co2Setting":"","co2Level":"","setBy":"Schedule","frontKeypad":"On","runStatus":"Off","auxStatus":"Off","setback":"Off"},{"timestamp":"2025-08-30T12:33","system":"Auto","heatSetting":60,"coolSetting":85,"fan":"Auto","status":"Occupied","temperature":77,"humidity":0,"humidifySetting":0,"dehumidifySetting":0,"co2Setting":"","co2Level":"","setBy":"Schedule","frontKeypad":"On","runStatus":"Off","auxStatus":"Off","setback":"Off"},{"timestamp":"2025-08-30T12:39","system":"Auto","heatSetting":60,"coolSetting":85,"fan":"Auto","status":"Occupied","temperature":77.1,"humidity":0,"humidifySetting":0,"dehumidifySetting":0,"co2Setting":"","co2Level":"","setBy":"Schedule","frontKeypad":"On","runStatus":"Off","auxStatus":"Off","setback":"Off"},{"timestamp":"2025-08-30T12:48","system":"Auto","heatSetting":60,"coolSetting":85,"fan":"Auto","status":"Occupied","temperature":77.2,"humidity":0,"humidifySetting":0,"dehumidifySetting":0,"co2Setting":"","co2Level":"","setBy":"Schedule","frontKeypad":"On","runStatus":"Off","auxStatus":"Off","setback":"Off"},{"timestamp":"2025-08-30T12:56","system":"Auto","heatSetting":60,"coolSetting":85,"fan":"Auto","status":"Occupied","temperature":77.3,"humidity":0,"humidifySetting":0,"dehumidifySetting":0,"co2Setting":"","co2Level":"","setBy":"Schedule","frontKeypad":"On","runStatus":"Off","auxStatus":"Off","setback":"Off"},{"timestamp":"2025-08-30T13:06","system":"Auto","heatSetting":60,"coolSetting":85,"fan":"Auto","status":"Occupied","temperature":77.4,"humidity":0,"humidifySetting":0,"dehumidifySetting":0,"co2Setting":"","co2Level":"","setBy":"Schedule","frontKeypad":"On","runStatus":"Off","auxStatus":"Off","setback":"Off"},{"timestamp":"2025-08-30T13:14","system":"Auto","heatSetting":60,"coolSetting":85,"fan":"Auto","status":"Occupied","temperature":77.5,"humidity":0,"humidifySetting":0,"dehumidifySetting":0,"co2Setting":"","co2Level":"","setBy":"Schedule","frontKeypad":"On","runStatus":"Off","auxStatus":"Off","setback":"Off"},{"timestamp":"2025-08-30T13:20","system":"Auto","heatSetting":60,"coolSetting":85,"fan":"Auto","status":"Occupied","temperature":77.6,"humidity":0,"humidifySetting":0,"dehumidifySetting":0,"co2Setting":"","co2Level":"","setBy":"Schedule","frontKeypad":"On","runStatus":"Off","auxStatus":"Off","setback":"Off"},{"timestamp":"2025-08-30T13:31","system":"Auto","heatSetting":60,"coolSetting":85,"fan":"Auto","status":"Occupied","temperature":77.8,"humidity":0,"humidifySetting":0,"dehumidifySetting":0,"co2Setting":"","co2Level":"","setBy":"Schedule","frontKeypad":"On","runStatus":"Off","auxStatus":"Off","setback":"Off"},{"timestamp":"2025-08-30T13:38","system":"Auto","heatSetting":60,"coolSetting":85,"fan":"Auto","status":"Occupied","temperature":77.9,"humidity":0,"humidifySetting":0,"dehumidifySetting":0,"co2Setting":"","co2Level":"","setBy":"Schedule","frontKeypad":"On","runStatus":"Off","auxStatus":"Off","setback":"Off"},{"timestamp":"2025-08-30T13:46","system":"Auto","heatSetting":60,"coolSetting":85,"fan":"Auto","status":"Occupied","temperature":78,"humidity":0,"humidifySetting":0,"dehumidifySetting":0,"co2Setting":"","co2Level":"","setBy":"Schedule","frontKeypad":"On","runStatus":"Off","auxStatus":"Off","setback":"Off"},{"timestamp":"2025-08-30T13:57","system":"Auto","heatSetting":60,"coolSetting":85,"fan":"Auto","status":"Occupied","temperature":78.1,"humidity":0,"humidifySetting":0,"dehumidifySetting":0,"co2Setting":"","co2Level":"","setBy":"Schedule","frontKeypad":"On","runStatus":"Off","auxStatus":"Off","setback":"Off"},{"timestamp":"2025-08-30T14:07","system":"Auto","heatSetting":60,"coolSetting":85,"fan":"Auto","status":"Occupied","temperature":78.2,"humidity":0,"humidifySetting":0,"dehumidifySetting":0,"co2Setting":"","co2Level":"","setBy":"Schedule","frontKeypad":"On","runStatus":"Off","auxStatus":"Off","setback":"Off"},{"timestamp":"2025-08-30T14:17","system":"Auto","heatSetting":60,"coolSetting":85,"fan":"Auto","status":"Occupied","temperature":78.3,"humidity":0,"humidifySetting":0,"dehumidifySetting":0,"co2Setting":"","co2Level":"","setBy":"Schedule","frontKeypad":"On","runStatus":"Off","auxStatus":"Off","setback":"Off"},{"timestamp":"2025-08-30T14:24","system":"Auto","heatSetting":60,"coolSetting":85,"fan":"Auto","status":"Occupied","temperature":78.4,"humidity":0,"humidifySetting":0,"dehumidifySetting":0,"co2Setting":"","co2Level":"","setBy":"Schedule","frontKeypad":"On","runStatus":"Off","auxStatus":"Off","setback":"Off"},{"timestamp":"2025-08-30T14:35","system":"Auto","heatSetting":60,"coolSetting":85,"fan":"Auto","status":"Occupied","temperature":78.5,"humidity":0,"humidifySetting":0,"dehumidifySetting":0,"co2Setting":"","co2Level":"","setBy":"Schedule","frontKeypad":"On","runStatus":"Off","auxStatus":"Off","setback":"Off"},{"timestamp":"2025-08-30T14:45","system":"Auto","heatSetting":60,"coolSetting":85,"fan":"Auto","status":"Occupied","temperature":78.7,"humidity":0,"humidifySetting":0,"dehumidifySetting":0,"co2Setting":"","co2Level":"","setBy":"Schedule","frontKeypad":"On","runStatus":"Off","auxStatus":"Off","setback":"Off"},{"timestamp":"2025-08-30T15:00","system":"Auto","heatSetting":60,"coolSetting":85,"fan":"Auto","status":"Occupied","temperature":78.8,"humidity":0,"humidifySetting":0,"dehumidifySetting":0,"co2Setting":"","co2Level":"","setBy":"Schedule","frontKeypad":"On","runStatus":"Off","auxStatus":"Off","setback":"Off"},{"timestamp":"2025-08-30T15:07","system":"Auto","heatSetting":60,"coolSetting":85,"fan":"Auto","status":"Occupied","temperature":78.9,"humidity":0,"humidifySetting":0,"dehumidifySetting":0,"co2Setting":"","co2Level":"","setBy":"Schedule","frontKeypad":"On","runStatus":"Off","auxStatus":"Off","setback":"Off"},{"timestamp":"2025-08-30T15:21","system":"Auto","heatSetting":60,"coolSetting":85,"fan":"Auto","status":"Occupied","temperature":79,"humidity":0,"humidifySetting":0,"dehumidifySetting":0,"co2Setting":"","co2Level":"","setBy":"Schedule","frontKeypad":"On","runStatus":"Off","auxStatus":"Off","setback":"Off"},{"timestamp":"2025-08-30T15:25","system":"Auto","heatSetting":60,"coolSetting":85,"fan":"Auto","status":"Occupied","temperature":78.9,"humidity":0,"humidifySetting":0,"dehumidifySetting":0,"co2Setting":"","co2Level":"","setBy":"Schedule","frontKeypad":"On","runStatus":"Off","auxStatus":"Off","setback":"Off"},{"timestamp":"2025-08-30T15:27","system":"Auto","heatSetting":60,"coolSetting":85,"fan":"Auto","status":"Occupied","temperature":79,"humidity":0,"humidifySetting":0,"dehumidifySetting":0,"co2Setting":"","co2Level":"","setBy":"Schedule","frontKeypad":"On","runStatus":"Off","auxStatus":"Off","setback":"Off"},{"timestamp":"2025-08-30T15:38","system":"Auto","heatSetting":60,"coolSetting":85,"fan":"Auto","status":"Occupied","temperature":79.1,"humidity":0,"humidifySetting":0,"dehumidifySetting":0,"co2Setting":"","co2Level":"","setBy":"Schedule","frontKeypad":"On","runStatus":"Off","auxStatus":"Off","setback":"Off"},{"timestamp":"2025-08-30T15:51","system":"Auto","heatSetting":60,"coolSetting":85,"fan":"Auto","status":"Occupied","temperature":79.2,"humidity":0,"humidifySetting":0,"dehumidifySetting":0,"co2Setting":"","co2Level":"","setBy":"Schedule","frontKeypad":"On","runStatus":"Off","auxStatus":"Off","setback":"Off"},{"timestamp":"2025-08-30T16:03","system":"Auto","heatSetting":60,"coolSetting":85,"fan":"Auto","status":"Occupied","temperature":79.3,"humidity":0,"humidifySetting":0,"dehumidifySetting":0,"co2Setting":"","co2Level":"","setBy":"Schedule","frontKeypad":"On","runStatus":"Off","auxStatus":"Off","setback":"Off"},{"timestamp":"2025-08-30T16:17","system":"Auto","heatSetting":60,"coolSetting":85,"fan":"Auto","status":"Occupied","temperature":79.4,"humidity":0,"humidifySetting":0,"dehumidifySetting":0,"co2Setting":"","co2Level":"","setBy":"Schedule","frontKeypad":"On","runStatus":"Off","auxStatus":"Off","setback":"Off"},{"timestamp":"2025-08-30T16:30","system":"Auto","heatSetting":60,"coolSetting":85,"fan":"Auto","status":"Occupied","temperature":79.6,"humidity":0,"humidifySetting":0,"dehumidifySetting":0,"co2Setting":"","co2Level":"","setBy":"Schedule","frontKeypad":"On","runStatus":"Off","auxStatus":"Off","setback":"Off"},{"timestamp":"2025-08-30T16:48","system":"Auto","heatSetting":60,"coolSetting":85,"fan":"Auto","status":"Occupied","temperature":79.7,"humidity":0,"humidifySetting":0,"dehumidifySetting":0,"co2Setting":"","co2Level":"","setBy":"Schedule","frontKeypad":"On","runStatus":"Off","auxStatus":"Off","setback":"Off"},{"timestamp":"2025-08-30T16:57","system":"Auto","heatSetting":60,"coolSetting":85,"fan":"Auto","status":"Occupied","temperature":79.8,"humidity":0,"humidifySetting":0,"dehumidifySetting":0,"co2Setting":"","co2Level":"","setBy":"Schedule","frontKeypad":"On","runStatus":"Off","auxStatus":"Off","setback":"Off"},{"timestamp":"2025-08-30T17:07","system":"Auto","heatSetting":60,"coolSetting":85,"fan":"Auto","status":"Occupied","temperature":79.9,"humidity":0,"humidifySetting":0,"dehumidifySetting":0,"co2Setting":"","co2Level":"","setBy":"Schedule","frontKeypad":"On","runStatus":"Off","auxStatus":"Off","setback":"Off"},{"timestamp":"2025-08-30T17:15","system":"Auto","heatSetting":60,"coolSetting":85,"fan":"Auto","status":"Occupied","temperature":80,"humidity":0,"humidifySetting":0,"dehumidifySetting":0,"co2Setting":"","co2Level":"","setBy":"Schedule","frontKeypad":"On","runStatus":"Off","auxStatus":"Off","setback":"Off"},{"timestamp":"2025-08-30T17:21","system":"Auto","heatSetting":60,"coolSetting":85,"fan":"Auto","status":"Occupied","temperature":80.1,"humidity":0,"humidifySetting":0,"dehumidifySetting":0,"co2Setting":"","co2Level":"","setBy":"Schedule","frontKeypad":"On","runStatus":"Off","auxStatus":"Off","setback":"Off"},{"timestamp":"2025-08-30T17:26","system":"Auto","heatSetting":60,"coolSetting":85,"fan":"Auto","status":"Occupied","temperature":80.2,"humidity":0,"humidifySetting":0,"dehumidifySetting":0,"co2Setting":"","co2Level":"","setBy":"Schedule","frontKeypad":"On","runStatus":"Off","auxStatus":"Off","setback":"Off"},{"timestamp":"2025-08-30T17:55","system":"Auto","heatSetting":60,"coolSetting":85,"fan":"Auto","status":"Occupied","temperature":80.1,"humidity":0,"humidifySetting":0,"dehumidifySetting":0,"co2Setting":"","co2Level":"","setBy":"Schedule","frontKeypad":"On","runStatus":"Off","auxStatus":"Off","setback":"Off"},{"timestamp":"2025-08-30T18:18","system":"Auto","heatSetting":60,"coolSetting":85,"fan":"Auto","status":"Occupied","temperature":80.2,"humidity":0,"humidifySetting":0,"dehumidifySetting":0,"co2Setting":"","co2Level":"","setBy":"Schedule","frontKeypad":"On","runStatus":"Off","auxStatus":"Off","setback":"Off"},{"timestamp":"2025-08-30T18:27","system":"Auto","heatSetting":60,"coolSetting":85,"fan":"Auto","status":"Occupied","temperature":80.3,"humidity":0,"humidifySetting":0,"dehumidifySetting":0,"co2Setting":"","co2Level":"","setBy":"Schedule","frontKeypad":"On","runStatus":"Off","auxStatus":"Off","setback":"Off"},{"timestamp":"2025-08-30T18:39","system":"Auto","heatSetting":60,"coolSetting":85,"fan":"Auto","status":"Occupied","temperature":80.5,"humidity":0,"humidifySetting":0,"dehumidifySetting":0,"co2Setting":"","co2Level":"","setBy":"Schedule","frontKeypad":"On","runStatus":"Off","auxStatus":"Off","setback":"Off"},{"timestamp":"2025-08-30T18:49","system":"Auto","heatSetting":60,"coolSetting":85,"fan":"Auto","status":"Occupied","temperature":80.6,"humidity":0,"humidifySetting":0,"dehumidifySetting":0,"co2Setting":"","co2Level":"","setBy":"Schedule","frontKeypad":"On","runStatus":"Off","auxStatus":"Off","setback":"Off"},{"timestamp":"2025-08-30T19:06","system":"Auto","heatSetting":60,"coolSetting":85,"fan":"Auto","status":"Occupied","temperature":80.7,"humidity":0,"humidifySetting":0,"dehumidifySetting":0,"co2Setting":"","co2Level":"","setBy":"Schedule","frontKeypad":"On","runStatus":"Off","auxStatus":"Off","setback":"Off"},{"timestamp":"2025-08-30T19:35","system":"Auto","heatSetting":60,"coolSetting":85,"fan":"Auto","status":"Occupied","temperature":80.6,"humidity":0,"humidifySetting":0,"dehumidifySetting":0,"co2Setting":"","co2Level":"","setBy":"Schedule","frontKeypad":"On","runStatus":"Off","auxStatus":"Off","setback":"Off"},{"timestamp":"2025-08-30T19:46","system":"Auto","heatSetting":60,"coolSetting":85,"fan":"Auto","status":"Occupied","temperature":80.5,"humidity":0,"humidifySetting":0,"dehumidifySetting":0,"co2Setting":"","co2Level":"","setBy":"Schedule","frontKeypad":"On","runStatus":"Off","auxStatus":"Off","setback":"Off"},{"timestamp":"2025-08-30T19:57","system":"Auto","heatSetting":60,"coolSetting":85,"fan":"Auto","status":"Occupied","temperature":80.3,"humidity":0,"humidifySetting":0,"dehumidifySetting":0,"co2Setting":"","co2Level":"","setBy":"Schedule","frontKeypad":"On","runStatus":"Off","auxStatus":"Off","setback":"Off"},{"timestamp":"2025-08-30T20:07","system":"Auto","heatSetting":60,"coolSetting":85,"fan":"Auto","status":"Occupied","temperature":80.2,"humidity":0,"humidifySetting":0,"dehumidifySetting":0,"co2Setting":"","co2Level":"","setBy":"Schedule","frontKeypad":"On","runStatus":"Off","auxStatus":"Off","setback":"Off"},{"timestamp":"2025-08-30T20:16","system":"Auto","heatSetting":60,"coolSetting":85,"fan":"Auto","status":"Occupied","temperature":80.1,"humidity":0,"humidifySetting":0,"dehumidifySetting":0,"co2Setting":"","co2Level":"","setBy":"Schedule","frontKeypad":"On","runStatus":"Off","auxStatus":"Off","setback":"Off"},{"timestamp":"2025-08-30T20:29","system":"Auto","heatSetting":60,"coolSetting":85,"fan":"Auto","status":"Occupied","temperature":80,"humidity":0,"humidifySetting":0,"dehumidifySetting":0,"co2Setting":"","co2Level":"","setBy":"Schedule","frontKeypad":"On","runStatus":"Off","auxStatus":"Off","setback":"Off"},{"timestamp":"2025-08-30T20:42","system":"Auto","heatSetting":60,"coolSetting":85,"fan":"Auto","status":"Occupied","temperature":79.9,"humidity":0,"humidifySetting":0,"dehumidifySetting":0,"co2Setting":"","co2Level":"","setBy":"Schedule","frontKeypad":"On","runStatus":"Off","auxStatus":"Off","setback":"Off"},{"timestamp":"2025-08-30T21:03","system":"Auto","heatSetting":60,"coolSetting":85,"fan":"Auto","status":"Occupied","temperature":79.8,"humidity":0,"humidifySetting":0,"dehumidifySetting":0,"co2Setting":"","co2Level":"","setBy":"Schedule","frontKeypad":"On","runStatus":"Off","auxStatus":"Off","setback":"Off"},{"timestamp":"2025-08-30T21:07","system":"Auto","heatSetting":60,"coolSetting":85,"fan":"Auto","status":"Occupied","temperature":79.9,"humidity":0,"humidifySetting":0,"dehumidifySetting":0,"co2Setting":"","co2Level":"","setBy":"Schedule","frontKeypad":"On","runStatus":"Off","auxStatus":"Off","setback":"Off"},{"timestamp":"2025-08-30T21:12","system":"Auto","heatSetting":60,"coolSetting":85,"fan":"Auto","status":"Occupied","temperature":79.8,"humidity":0,"humidifySetting":0,"dehumidifySetting":0,"co2Setting":"","co2Level":"","setBy":"Schedule","frontKeypad":"On","runStatus":"Off","auxStatus":"Off","setback":"Off"},{"timestamp":"2025-08-30T21:28","system":"Auto","heatSetting":60,"coolSetting":85,"fan":"Auto","status":"Occupied","temperature":79.7,"humidity":0,"humidifySetting":0,"dehumidifySetting":0,"co2Setting":"","co2Level":"","setBy":"Schedule","frontKeypad":"On","runStatus":"Off","auxStatus":"Off","setback":"Off"},{"timestamp":"2025-08-30T21:48","system":"Auto","heatSetting":60,"coolSetting":85,"fan":"Auto","status":"Occupied","temperature":79.6,"humidity":0,"humidifySetting":0,"dehumidifySetting":0,"co2Setting":"","co2Level":"","setBy":"Schedule","frontKeypad":"On","runStatus":"Off","auxStatus":"Off","setback":"Off"},{"timestamp":"2025-08-30T22:00","system":"Auto","heatSetting":60,"coolSetting":85,"fan":"Auto","status":"Occupied","temperature":79.6,"humidity":0,"humidifySetting":0,"dehumidifySetting":0,"co2Setting":"","co2Level":"","setBy":"Schedule","frontKeypad":"On","runStatus":"Off","auxStatus":"Off","setback":"Off"},{"timestamp":"2025-08-30T22:27","system":"Auto","heatSetting":60,"coolSetting":85,"fan":"Auto","status":"Occupied","temperature":79.4,"humidity":0,"humidifySetting":0,"dehumidifySetting":0,"co2Setting":"","co2Level":"","setBy":"Schedule","frontKeypad":"On","runStatus":"Off","auxStatus":"Off","setback":"Off"},{"timestamp":"2025-08-30T22:32","system":"Auto","heatSetting":60,"coolSetting":85,"fan":"Auto","status":"Occupied","temperature":79.6,"humidity":0,"humidifySetting":0,"dehumidifySetting":0,"co2Setting":"","co2Level":"","setBy":"Schedule","frontKeypad":"On","runStatus":"Off","auxStatus":"Off","setback":"Off"},{"timestamp":"2025-08-30T22:37","system":"Auto","heatSetting":60,"coolSetting":85,"fan":"Auto","status":"Occupied","temperature":79.4,"humidity":0,"humidifySetting":0,"dehumidifySetting":0,"co2Setting":"","co2Level":"","setBy":"Schedule","frontKeypad":"On","runStatus":"Off","auxStatus":"Off","setback":"Off"},{"timestamp":"2025-08-30T23:01","system":"Auto","heatSetting":60,"coolSetting":85,"fan":"Auto","status":"Occupied","temperature":79.3,"humidity":0,"humidifySetting":0,"dehumidifySetting":0,"co2Setting":"","co2Level":"","setBy":"Schedule","frontKeypad":"On","runStatus":"Off","auxStatus":"Off","setback":"Off"},{"timestamp":"2025-08-30T23:29","system":"Auto","heatSetting":60,"coolSetting":85,"fan":"Auto","status":"Occupied","temperature":79.2,"humidity":0,"humidifySetting":0,"dehumidifySetting":0,"co2Setting":"","co2Level":"","setBy":"Schedule","frontKeypad":"On","runStatus":"Off","auxStatus":"Off","setback":"Off"},{"timestamp":"2025-08-30T23:34","system":"Auto","heatSetting":60,"coolSetting":85,"fan":"Auto","status":"Occupied","temperature":79.3,"humidity":0,"humidifySetting":0,"dehumidifySetting":0,"co2Setting":"","co2Level":"","setBy":"Schedule","frontKeypad":"On","runStatus":"Off","auxStatus":"Off","setback":"Off"},{"timestamp":"2025-08-30T23:39","system":"Auto","heatSetting":60,"coolSetting":85,"fan":"Auto","status":"Occupied","temperature":79.2,"humidity":0,"humidifySetting":0,"dehumidifySetting":0,"co2Setting":"","co2Level":"","setBy":"Schedule","frontKeypad":"On","runStatus":"Off","auxStatus":"Off","setback":"Off"},{"timestamp":"2025-08-31T00:12","system":"Auto","heatSetting":60,"coolSetting":85,"fan":"Auto","status":"Occupied","temperature":79.1,"humidity":0,"humidifySetting":0,"dehumidifySetting":0,"co2Setting":"","co2Level":"","setBy":"Schedule","frontKeypad":"On","runStatus":"Off","auxStatus":"Off","setback":"Off"},{"timestamp":"2025-08-31T00:17","system":"Auto","heatSetting":60,"coolSetting":85,"fan":"Auto","status":"Occupied","temperature":79.2,"humidity":0,"humidifySetting":0,"dehumidifySetting":0,"co2Setting":"","co2Level":"","setBy":"Schedule","frontKeypad":"On","runStatus":"Off","auxStatus":"Off","setback":"Off"},{"timestamp":"2025-08-31T00:22","system":"Auto","heatSetting":60,"coolSetting":85,"fan":"Auto","status":"Occupied","temperature":79.1,"humidity":0,"humidifySetting":0,"dehumidifySetting":0,"co2Setting":"","co2Level":"","setBy":"Schedule","frontKeypad":"On","runStatus":"Off","auxStatus":"Off","setback":"Off"},{"timestamp":"2025-08-31T00:27","system":"Auto","heatSetting":60,"coolSetting":85,"fan":"Auto","status":"Occupied","temperature":79.2,"humidity":0,"humidifySetting":0,"dehumidifySetting":0,"co2Setting":"","co2Level":"","setBy":"Schedule","frontKeypad":"On","runStatus":"Off","auxStatus":"Off","setback":"Off"},{"timestamp":"2025-08-31T00:33","system":"Auto","heatSetting":60,"coolSetting":85,"fan":"Auto","status":"Occupied","temperature":79.1,"humidity":0,"humidifySetting":0,"dehumidifySetting":0,"co2Setting":"","co2Level":"","setBy":"Schedule","frontKeypad":"On","runStatus":"Off","auxStatus":"Off","setback":"Off"},{"timestamp":"2025-08-31T01:07","system":"Auto","heatSetting":60,"coolSetting":85,"fan":"Auto","status":"Occupied","temperature":79,"humidity":0,"humidifySetting":0,"dehumidifySetting":0,"co2Setting":"","co2Level":"","setBy":"Schedule","frontKeypad":"On","runStatus":"Off","auxStatus":"Off","setback":"Off"},{"timestamp":"2025-08-31T01:34","system":"Auto","heatSetting":60,"coolSetting":85,"fan":"Auto","status":"Occupied","temperature":79.1,"humidity":0,"humidifySetting":0,"dehumidifySetting":0,"co2Setting":"","co2Level":"","setBy":"Schedule","frontKeypad":"On","runStatus":"Off","auxStatus":"Off","setback":"Off"},{"timestamp":"2025-08-31T01:39","system":"Auto","heatSetting":60,"coolSetting":85,"fan":"Auto","status":"Occupied","temperature":79,"humidity":0,"humidifySetting":0,"dehumidifySetting":0,"co2Setting":"","co2Level":"","setBy":"Schedule","frontKeypad":"On","runStatus":"Off","auxStatus":"Off","setback":"Off"},{"timestamp":"2025-08-31T02:00","system":"Auto","heatSetting":60,"coolSetting":85,"fan":"Auto","status":"Occupied","temperature":79,"humidity":0,"humidifySetting":0,"dehumidifySetting":0,"co2Setting":"","co2Level":"","setBy":"Schedule","frontKeypad":"On","runStatus":"Off","auxStatus":"Off","setback":"Off"},{"timestamp":"2025-08-31T02:05","system":"Auto","heatSetting":60,"coolSetting":85,"fan":"Auto","status":"Occupied","temperature":78.9,"humidity":0,"humidifySetting":0,"dehumidifySetting":0,"co2Setting":"","co2Level":"","setBy":"Schedule","frontKeypad":"On","runStatus":"Off","auxStatus":"Off","setback":"Off"},{"timestamp":"2025-08-31T02:56","system":"Auto","heatSetting":60,"coolSetting":85,"fan":"Auto","status":"Occupied","temperature":78.8,"humidity":0,"humidifySetting":0,"dehumidifySetting":0,"co2Setting":"","co2Level":"","setBy":"Schedule","frontKeypad":"On","runStatus":"Off","auxStatus":"Off","setback":"Off"},{"timestamp":"2025-08-31T03:02","system":"Auto","heatSetting":60,"coolSetting":85,"fan":"Auto","status":"Occupied","temperature":78.9,"humidity":0,"humidifySetting":0,"dehumidifySetting":0,"co2Setting":"","co2Level":"","setBy":"Schedule","frontKeypad":"On","runStatus":"Off","auxStatus":"Off","setback":"Off"},{"timestamp":"2025-08-31T03:06","system":"Auto","heatSetting":60,"coolSetting":85,"fan":"Auto","status":"Occupied","temperature":78.8,"humidity":0,"humidifySetting":0,"dehumidifySetting":0,"co2Setting":"","co2Level":"","setBy":"Schedule","frontKeypad":"On","runStatus":"Off","auxStatus":"Off","setback":"Off"},{"timestamp":"2025-08-31T03:38","system":"Auto","heatSetting":60,"coolSetting":85,"fan":"Auto","status":"Occupied","temperature":78.8,"humidity":0,"humidifySetting":0,"dehumidifySetting":0,"co2Setting":"","co2Level":"","setBy":"Schedule","frontKeypad":"On","runStatus":"Off","auxStatus":"Off","setback":"Off"},{"timestamp":"2025-08-31T03:43","system":"Auto","heatSetting":60,"coolSetting":85,"fan":"Auto","status":"Occupied","temperature":78.7,"humidity":0,"humidifySetting":0,"dehumidifySetting":0,"co2Setting":"","co2Level":"","setBy":"Schedule","frontKeypad":"On","runStatus":"Off","auxStatus":"Off","setback":"Off"},{"timestamp":"2025-08-31T04:00","system":"Auto","heatSetting":60,"coolSetting":85,"fan":"Auto","status":"Occupied","temperature":78.7,"humidity":0,"humidifySetting":0,"dehumidifySetting":0,"co2Setting":"","co2Level":"","setBy":"Schedule","frontKeypad":"On","runStatus":"Off","auxStatus":"Off","setback":"Off"},{"timestamp":"2025-08-31T04:33","system":"Auto","heatSetting":60,"coolSetting":85,"fan":"Auto","status":"Occupied","temperature":78.5,"humidity":0,"humidifySetting":0,"dehumidifySetting":0,"co2Setting":"","co2Level":"","setBy":"Schedule","frontKeypad":"On","runStatus":"Off","auxStatus":"Off","setback":"Off"},{"timestamp":"2025-08-31T04:39","system":"Auto","heatSetting":60,"coolSetting":85,"fan":"Auto","status":"Occupied","temperature":78.7,"humidity":0,"humidifySetting":0,"dehumidifySetting":0,"co2Setting":"","co2Level":"","setBy":"Schedule","frontKeypad":"On","runStatus":"Off","auxStatus":"Off","setback":"Off"},{"timestamp":"2025-08-31T04:44","system":"Auto","heatSetting":60,"coolSetting":85,"fan":"Auto","status":"Occupied","temperature":78.5,"humidity":0,"humidifySetting":0,"dehumidifySetting":0,"co2Setting":"","co2Level":"","setBy":"Schedule","frontKeypad":"On","runStatus":"Off","auxStatus":"Off","setback":"Off"},{"timestamp":"2025-08-31T05:27","system":"Auto","heatSetting":60,"coolSetting":85,"fan":"Auto","status":"Occupied","temperature":78.4,"humidity":0,"humidifySetting":0,"dehumidifySetting":0,"co2Setting":"","co2Level":"","setBy":"Schedule","frontKeypad":"On","runStatus":"Off","auxStatus":"Off","setback":"Off"},{"timestamp":"2025-08-31T05:37","system":"Auto","heatSetting":60,"coolSetting":85,"fan":"Auto","status":"Occupied","temperature":78.5,"humidity":0,"humidifySetting":0,"dehumidifySetting":0,"co2Setting":"","co2Level":"","setBy":"Schedule","frontKeypad":"On","runStatus":"Off","auxStatus":"Off","setback":"Off"},{"timestamp":"2025-08-31T05:42","system":"Auto","heatSetting":60,"coolSetting":85,"fan":"Auto","status":"Occupied","temperature":78.4,"humidity":0,"humidifySetting":0,"dehumidifySetting":0,"co2Setting":"","co2Level":"","setBy":"Schedule","frontKeypad":"On","runStatus":"Off","auxStatus":"Off","setback":"Off"},{"timestamp":"2025-08-31T06:00","system":"Auto","heatSetting":60,"coolSetting":85,"fan":"Auto","status":"Occupied","temperature":78.4,"humidity":0,"humidifySetting":0,"dehumidifySetting":0,"co2Setting":"","co2Level":"","setBy":"Schedule","frontKeypad":"On","runStatus":"Off","auxStatus":"Off","setback":"Off"},{"timestamp":"2025-08-31T06:17","system":"Auto","heatSetting":60,"coolSetting":85,"fan":"Auto","status":"Occupied","temperature":78.3,"humidity":0,"humidifySetting":0,"dehumidifySetting":0,"co2Setting":"","co2Level":"","setBy":"Schedule","frontKeypad":"On","runStatus":"Off","auxStatus":"Off","setback":"Off"},{"timestamp":"2025-08-31T06:23","system":"Auto","heatSetting":60,"coolSetting":85,"fan":"Auto","status":"Occupied","temperature":78.4,"humidity":0,"humidifySetting":0,"dehumidifySetting":0,"co2Setting":"","co2Level":"","setBy":"Schedule","frontKeypad":"On","runStatus":"Off","auxStatus":"Off","setback":"Off"},{"timestamp":"2025-08-31T06:28","system":"Auto","heatSetting":60,"coolSetting":85,"fan":"Auto","status":"Occupied","temperature":78.3,"humidity":0,"humidifySetting":0,"dehumidifySetting":0,"co2Setting":"","co2Level":"","setBy":"Schedule","frontKeypad":"On","runStatus":"Off","auxStatus":"Off","setback":"Off"},{"timestamp":"2025-08-31T07:24","system":"Auto","heatSetting":60,"coolSetting":85,"fan":"Auto","status":"Occupied","temperature":78.2,"humidity":0,"humidifySetting":0,"dehumidifySetting":0,"co2Setting":"","co2Level":"","setBy":"Schedule","frontKeypad":"On","runStatus":"Off","auxStatus":"Off","setback":"Off"},{"timestamp":"2025-08-31T07:30","system":"Auto","heatSetting":60,"coolSetting":85,"fan":"Auto","status":"Occupied","temperature":78.3,"humidity":0,"humidifySetting":0,"dehumidifySetting":0,"co2Setting":"","co2Level":"","setBy":"Schedule","frontKeypad":"On","runStatus":"Off","auxStatus":"Off","setback":"Off"},{"timestamp":"2025-08-31T07:36","system":"Auto","heatSetting":60,"coolSetting":85,"fan":"Auto","status":"Occupied","temperature":78.2,"humidity":0,"humidifySetting":0,"dehumidifySetting":0,"co2Setting":"","co2Level":"","setBy":"Schedule","frontKeypad":"On","runStatus":"Off","auxStatus":"Off","setback":"Off"},{"timestamp":"2025-08-31T07:44","system":"Auto","heatSetting":60,"coolSetting":85,"fan":"Auto","status":"Occupied","temperature":78.3,"humidity":0,"humidifySetting":0,"dehumidifySetting":0,"co2Setting":"","co2Level":"","setBy":"Schedule","frontKeypad":"On","runStatus":"Off","auxStatus":"Off","setback":"Off"},{"timestamp":"2025-08-31T07:49","system":"Auto","heatSetting":60,"coolSetting":85,"fan":"Auto","status":"Occupied","temperature":78.2,"humidity":0,"humidifySetting":0,"dehumidifySetting":0,"co2Setting":"","co2Level":"","setBy":"Schedule","frontKeypad":"On","runStatus":"Off","auxStatus":"Off","setback":"Off"},{"timestamp":"2025-08-31T07:54","system":"Auto","heatSetting":60,"coolSetting":85,"fan":"Auto","status":"Occupied","temperature":78.3,"humidity":0,"humidifySetting":0,"dehumidifySetting":0,"co2Setting":"","co2Level":"","setBy":"Schedule","frontKeypad":"On","runStatus":"Off","auxStatus":"Off","setback":"Off"},{"timestamp":"2025-08-31T08:00","system":"Auto","heatSetting":60,"coolSetting":85,"fan":"Auto","status":"Occupied","temperature":78.2,"humidity":0,"humidifySetting":0,"dehumidifySetting":0,"co2Setting":"","co2Level":"","setBy":"Schedule","frontKeypad":"On","runStatus":"Off","auxStatus":"Off","setback":"Off"},{"timestamp":"2025-08-31T08:25","system":"Auto","heatSetting":60,"coolSetting":85,"fan":"Auto","status":"Occupied","temperature":78.3,"humidity":0,"humidifySetting":0,"dehumidifySetting":0,"co2Setting":"","co2Level":"","setBy":"Schedule","frontKeypad":"On","runStatus":"Off","auxStatus":"Off","setback":"Off"},{"timestamp":"2025-08-31T08:31","system":"Auto","heatSetting":60,"coolSetting":85,"fan":"Auto","status":"Occupied","temperature":78.2,"humidity":0,"humidifySetting":0,"dehumidifySetting":0,"co2Setting":"","co2Level":"","setBy":"Schedule","frontKeypad":"On","runStatus":"Off","auxStatus":"Off","setback":"Off"},{"timestamp":"2025-08-31T08:36","system":"Auto","heatSetting":60,"coolSetting":85,"fan":"Auto","status":"Occupied","temperature":78.3,"humidity":0,"humidifySetting":0,"dehumidifySetting":0,"co2Setting":"","co2Level":"","setBy":"Schedule","frontKeypad":"On","runStatus":"Off","auxStatus":"Off","setback":"Off"},{"timestamp":"2025-08-31T09:09","system":"Auto","heatSetting":60,"coolSetting":85,"fan":"Auto","status":"Occupied","temperature":78.4,"humidity":0,"humidifySetting":0,"dehumidifySetting":0,"co2Setting":"","co2Level":"","setBy":"Schedule","frontKeypad":"On","runStatus":"Off","auxStatus":"Off","setback":"Off"},{"timestamp":"2025-08-31T09:29","system":"Auto","heatSetting":60,"coolSetting":85,"fan":"Auto","status":"Occupied","temperature":78.5,"humidity":0,"humidifySetting":0,"dehumidifySetting":0,"co2Setting":"","co2Level":"","setBy":"Schedule","frontKeypad":"On","runStatus":"Off","auxStatus":"Off","setback":"Off"},{"timestamp":"2025-08-31T09:47","system":"Auto","heatSetting":60,"coolSetting":85,"fan":"Auto","status":"Occupied","temperature":78.7,"humidity":0,"humidifySetting":0,"dehumidifySetting":0,"co2Setting":"","co2Level":"","setBy":"Schedule","frontKeypad":"On","runStatus":"Off","auxStatus":"Off","setback":"Off"},{"timestamp":"2025-08-31T10:00","system":"Auto","heatSetting":60,"coolSetting":85,"fan":"Auto","status":"Occupied","temperature":78.7,"humidity":0,"humidifySetting":0,"dehumidifySetting":0,"co2Setting":"","co2Level":"","setBy":"Schedule","frontKeypad":"On","runStatus":"Off","auxStatus":"Off","setback":"Off"},{"timestamp":"2025-08-31T10:07","system":"Auto","heatSetting":60,"coolSetting":85,"fan":"Auto","status":"Occupied","temperature":78.8,"humidity":0,"humidifySetting":0,"dehumidifySetting":0,"co2Setting":"","co2Level":"","setBy":"Schedule","frontKeypad":"On","runStatus":"Off","auxStatus":"Off","setback":"Off"},{"timestamp":"2025-08-31T10:12","system":"Auto","heatSetting":60,"coolSetting":85,"fan":"Auto","status":"Occupied","temperature":78.7,"humidity":0,"humidifySetting":0,"dehumidifySetting":0,"co2Setting":"","co2Level":"","setBy":"Schedule","frontKeypad":"On","runStatus":"Off","auxStatus":"Off","setback":"Off"},{"timestamp":"2025-08-31T10:17","system":"Auto","heatSetting":60,"coolSetting":85,"fan":"Auto","status":"Occupied","temperature":78.8,"humidity":0,"humidifySetting":0,"dehumidifySetting":0,"co2Setting":"","co2Level":"","setBy":"Schedule","frontKeypad":"On","runStatus":"Off","auxStatus":"Off","setback":"Off"},{"timestamp":"2025-08-31T10:31","system":"Auto","heatSetting":60,"coolSetting":85,"fan":"Auto","status":"Occupied","temperature":78.9,"humidity":0,"humidifySetting":0,"dehumidifySetting":0,"co2Setting":"","co2Level":"","setBy":"Schedule","frontKeypad":"On","runStatus":"Off","auxStatus":"Off","setback":"Off"},{"timestamp":"2025-08-31T10:36","system":"Auto","heatSetting":60,"coolSetting":85,"fan":"Auto","status":"Occupied","temperature":78.8,"humidity":0,"humidifySetting":0,"dehumidifySetting":0,"co2Setting":"","co2Level":"","setBy":"Schedule","frontKeypad":"On","runStatus":"Off","auxStatus":"Off","setback":"Off"},{"timestamp":"2025-08-31T10:41","system":"Auto","heatSetting":60,"coolSetting":85,"fan":"Auto","status":"Occupied","temperature":78.9,"humidity":0,"humidifySetting":0,"dehumidifySetting":0,"co2Setting":"","co2Level":"","setBy":"Schedule","frontKeypad":"On","runStatus":"Off","auxStatus":"Off","setback":"Off"},{"timestamp":"2025-08-31T11:05","system":"Auto","heatSetting":60,"coolSetting":85,"fan":"Auto","status":"Occupied","temperature":79,"humidity":0,"humidifySetting":0,"dehumidifySetting":0,"co2Setting":"","co2Level":"","setBy":"Schedule","frontKeypad":"On","runStatus":"Off","auxStatus":"Off","setback":"Off"},{"timestamp":"2025-08-31T11:18","system":"Auto","heatSetting":60,"coolSetting":85,"fan":"Auto","status":"Occupied","temperature":79.1,"humidity":0,"humidifySetting":0,"dehumidifySetting":0,"co2Setting":"","co2Level":"","setBy":"Schedule","frontKeypad":"On","runStatus":"Off","auxStatus":"Off","setback":"Off"},{"timestamp":"2025-08-31T11:32","system":"Auto","heatSetting":60,"coolSetting":85,"fan":"Auto","status":"Occupied","temperature":79.2,"humidity":0,"humidifySetting":0,"dehumidifySetting":0,"co2Setting":"","co2Level":"","setBy":"Schedule","frontKeypad":"On","runStatus":"Off","auxStatus":"Off","setback":"Off"},{"timestamp":"2025-08-31T11:43","system":"Auto","heatSetting":60,"coolSetting":85,"fan":"Auto","status":"Occupied","temperature":79.3,"humidity":0,"humidifySetting":0,"dehumidifySetting":0,"co2Setting":"","co2Level":"","setBy":"Schedule","frontKeypad":"On","runStatus":"Off","auxStatus":"Off","setback":"Off"},{"timestamp":"2025-08-31T11:52","system":"Auto","heatSetting":60,"coolSetting":85,"fan":"Auto","status":"Occupied","temperature":79.4,"humidity":0,"humidifySetting":0,"dehumidifySetting":0,"co2Setting":"","co2Level":"","setBy":"Schedule","frontKeypad":"On","runStatus":"Off","auxStatus":"Off","setback":"Off"},{"timestamp":"2025-08-31T12:00","system":"Auto","heatSetting":60,"coolSetting":85,"fan":"Auto","status":"Occupied","temperature":79.4,"humidity":0,"humidifySetting":0,"dehumidifySetting":0,"co2Setting":"","co2Level":"","setBy":"Schedule","frontKeypad":"On","runStatus":"Off","auxStatus":"Off","setback":"Off"},{"timestamp":"2025-08-31T12:06","system":"Auto","heatSetting":60,"coolSetting":85,"fan":"Auto","status":"Occupied","temperature":79.6,"humidity":0,"humidifySetting":0,"dehumidifySetting":0,"co2Setting":"","co2Level":"","setBy":"Schedule","frontKeypad":"On","runStatus":"Off","auxStatus":"Off","setback":"Off"},{"timestamp":"2025-08-31T12:15","system":"Auto","heatSetting":60,"coolSetting":85,"fan":"Auto","status":"Occupied","temperature":79.7,"humidity":0,"humidifySetting":0,"dehumidifySetting":0,"co2Setting":"","co2Level":"","setBy":"Schedule","frontKeypad":"On","runStatus":"Off","auxStatus":"Off","setback":"Off"},{"timestamp":"2025-08-31T12:25","system":"Auto","heatSetting":60,"coolSetting":85,"fan":"Auto","status":"Occupied","temperature":79.8,"humidity":0,"humidifySetting":0,"dehumidifySetting":0,"co2Setting":"","co2Level":"","setBy":"Schedule","frontKeypad":"On","runStatus":"Off","auxStatus":"Off","setback":"Off"},{"timestamp":"2025-08-31T12:31","system":"Auto","heatSetting":60,"coolSetting":85,"fan":"Auto","status":"Occupied","temperature":79.9,"humidity":0,"humidifySetting":0,"dehumidifySetting":0,"co2Setting":"","co2Level":"","setBy":"Schedule","frontKeypad":"On","runStatus":"Off","auxStatus":"Off","setback":"Off"},{"timestamp":"2025-08-31T12:45","system":"Auto","heatSetting":60,"coolSetting":85,"fan":"Auto","status":"Occupied","temperature":80,"humidity":0,"humidifySetting":0,"dehumidifySetting":0,"co2Setting":"","co2Level":"","setBy":"Schedule","frontKeypad":"On","runStatus":"Off","auxStatus":"Off","setback":"Off"},{"timestamp":"2025-08-31T12:54","system":"Auto","heatSetting":60,"coolSetting":85,"fan":"Auto","status":"Occupied","temperature":80.1,"humidity":0,"humidifySetting":0,"dehumidifySetting":0,"co2Setting":"","co2Level":"","setBy":"Schedule","frontKeypad":"On","runStatus":"Off","auxStatus":"Off","setback":"Off"},{"timestamp":"2025-08-31T13:10","system":"Auto","heatSetting":60,"coolSetting":85,"fan":"Auto","status":"Occupied","temperature":80.2,"humidity":0,"humidifySetting":0,"dehumidifySetting":0,"co2Setting":"","co2Level":"","setBy":"Schedule","frontKeypad":"On","runStatus":"Off","auxStatus":"Off","setback":"Off"},{"timestamp":"2025-08-31T13:16","system":"Auto","heatSetting":60,"coolSetting":85,"fan":"Auto","status":"Occupied","temperature":80.3,"humidity":0,"humidifySetting":0,"dehumidifySetting":0,"co2Setting":"","co2Level":"","setBy":"Schedule","frontKeypad":"On","runStatus":"Off","auxStatus":"Off","setback":"Off"},{"timestamp":"2025-08-31T13:28","system":"Auto","heatSetting":60,"coolSetting":85,"fan":"Auto","status":"Occupied","temperature":80.5,"humidity":0,"humidifySetting":0,"dehumidifySetting":0,"co2Setting":"","co2Level":"","setBy":"Schedule","frontKeypad":"On","runStatus":"Off","auxStatus":"Off","setback":"Off"},{"timestamp":"2025-08-31T13:38","system":"Auto","heatSetting":60,"coolSetting":85,"fan":"Auto","status":"Occupied","temperature":80.6,"humidity":0,"humidifySetting":0,"dehumidifySetting":0,"co2Setting":"","co2Level":"","setBy":"Schedule","frontKeypad":"On","runStatus":"Off","auxStatus":"Off","setback":"Off"},{"timestamp":"2025-08-31T13:51","system":"Auto","heatSetting":60,"coolSetting":85,"fan":"Auto","status":"Occupied","temperature":80.7,"humidity":0,"humidifySetting":0,"dehumidifySetting":0,"co2Setting":"","co2Level":"","setBy":"Schedule","frontKeypad":"On","runStatus":"Off","auxStatus":"Off","setback":"Off"},{"timestamp":"2025-08-31T14:00","system":"Auto","heatSetting":60,"coolSetting":85,"fan":"Auto","status":"Occupied","temperature":80.7,"humidity":0,"humidifySetting":0,"dehumidifySetting":0,"co2Setting":"","co2Level":"","setBy":"Schedule","frontKeypad":"On","runStatus":"Off","auxStatus":"Off","setback":"Off"},{"timestamp":"2025-08-31T14:01","system":"Auto","heatSetting":60,"coolSetting":85,"fan":"Auto","status":"Occupied","temperature":80.8,"humidity":0,"humidifySetting":0,"dehumidifySetting":0,"co2Setting":"","co2Level":"","setBy":"Schedule","frontKeypad":"On","runStatus":"Off","auxStatus":"Off","setback":"Off"},{"timestamp":"2025-08-31T14:14","system":"Auto","heatSetting":60,"coolSetting":85,"fan":"Auto","status":"Occupied","temperature":80.9,"humidity":0,"humidifySetting":0,"dehumidifySetting":0,"co2Setting":"","co2Level":"","setBy":"Schedule","frontKeypad":"On","runStatus":"Off","auxStatus":"Off","setback":"Off"},{"timestamp":"2025-08-31T14:25","system":"Auto","heatSetting":60,"coolSetting":85,"fan":"Auto","status":"Occupied","temperature":81,"humidity":0,"humidifySetting":0,"dehumidifySetting":0,"co2Setting":"","co2Level":"","setBy":"Schedule","frontKeypad":"On","runStatus":"Off","auxStatus":"Off","setback":"Off"},{"timestamp":"2025-08-31T14:34","system":"Auto","heatSetting":60,"coolSetting":85,"fan":"Auto","status":"Occupied","temperature":81.1,"humidity":0,"humidifySetting":0,"dehumidifySetting":0,"co2Setting":"","co2Level":"","setBy":"Schedule","frontKeypad":"On","runStatus":"Off","auxStatus":"Off","setback":"Off"},{"timestamp":"2025-08-31T14:48","system":"Auto","heatSetting":60,"coolSetting":85,"fan":"Auto","status":"Occupied","temperature":81.2,"humidity":0,"humidifySetting":0,"dehumidifySetting":0,"co2Setting":"","co2Level":"","setBy":"Schedule","frontKeypad":"On","runStatus":"Off","auxStatus":"Off","setback":"Off"},{"timestamp":"2025-08-31T15:01","system":"Auto","heatSetting":60,"coolSetting":85,"fan":"Auto","status":"Occupied","temperature":81.4,"humidity":0,"humidifySetting":0,"dehumidifySetting":0,"co2Setting":"","co2Level":"","setBy":"Schedule","frontKeypad":"On","runStatus":"Off","auxStatus":"Off","setback":"Off"},{"timestamp":"2025-08-31T15:12","system":"Auto","heatSetting":60,"coolSetting":85,"fan":"Auto","status":"Occupied","temperature":81.5,"humidity":0,"humidifySetting":0,"dehumidifySetting":0,"co2Setting":"","co2Level":"","setBy":"Schedule","frontKeypad":"On","runStatus":"Off","auxStatus":"Off","setback":"Off"},{"timestamp":"2025-08-31T15:25","system":"Auto","heatSetting":60,"coolSetting":85,"fan":"Auto","status":"Occupied","temperature":81.6,"humidity":0,"humidifySetting":0,"dehumidifySetting":0,"co2Setting":"","co2Level":"","setBy":"Schedule","frontKeypad":"On","runStatus":"Off","auxStatus":"Off","setback":"Off"},{"timestamp":"2025-08-31T15:39","system":"Auto","heatSetting":60,"coolSetting":85,"fan":"Auto","status":"Occupied","temperature":81.7,"humidity":0,"humidifySetting":0,"dehumidifySetting":0,"co2Setting":"","co2Level":"","setBy":"Schedule","frontKeypad":"On","runStatus":"Off","auxStatus":"Off","setback":"Off"},{"timestamp":"2025-08-31T15:52","system":"Auto","heatSetting":60,"coolSetting":85,"fan":"Auto","status":"Occupied","temperature":81.8,"humidity":0,"humidifySetting":0,"dehumidifySetting":0,"co2Setting":"","co2Level":"","setBy":"Schedule","frontKeypad":"On","runStatus":"Off","auxStatus":"Off","setback":"Off"},{"timestamp":"2025-08-31T16:03","system":"Auto","heatSetting":60,"coolSetting":85,"fan":"Auto","status":"Occupied","temperature":81.9,"humidity":0,"humidifySetting":0,"dehumidifySetting":0,"co2Setting":"","co2Level":"","setBy":"Schedule","frontKeypad":"On","runStatus":"Off","auxStatus":"Off","setback":"Off"},{"timestamp":"2025-08-31T16:20","system":"Auto","heatSetting":60,"coolSetting":85,"fan":"Auto","status":"Occupied","temperature":82,"humidity":0,"humidifySetting":0,"dehumidifySetting":0,"co2Setting":"","co2Level":"","setBy":"Schedule","frontKeypad":"On","runStatus":"Off","auxStatus":"Off","setback":"Off"},{"timestamp":"2025-08-31T17:20","system":"Auto","heatSetting":60,"coolSetting":85,"fan":"Auto","status":"Occupied","temperature":82,"humidity":0,"humidifySetting":0,"dehumidifySetting":0,"co2Setting":"","co2Level":"","setBy":"Schedule","frontKeypad":"On","runStatus":"Off","auxStatus":"Off","setback":"Off"},{"timestamp":"2025-08-31T17:32","system":"Auto","heatSetting":60,"coolSetting":85,"fan":"Auto","status":"Occupied","temperature":81.9,"humidity":0,"humidifySetting":0,"dehumidifySetting":0,"co2Setting":"","co2Level":"","setBy":"Schedule","frontKeypad":"On","runStatus":"Off","auxStatus":"Off","setback":"Off"},{"timestamp":"2025-08-31T17:36","system":"Auto","heatSetting":60,"coolSetting":85,"fan":"Auto","status":"Occupied","temperature":82,"humidity":0,"humidifySetting":0,"dehumidifySetting":0,"co2Setting":"","co2Level":"","setBy":"Schedule","frontKeypad":"On","runStatus":"Off","auxStatus":"Off","setback":"Off"},{"timestamp":"2025-08-31T17:38","system":"Auto","heatSetting":60,"coolSetting":85,"fan":"Auto","status":"Occupied","temperature":81.9,"humidity":0,"humidifySetting":0,"dehumidifySetting":0,"co2Setting":"","co2Level":"","setBy":"Schedule","frontKeypad":"On","runStatus":"Off","auxStatus":"Off","setback":"Off"},{"timestamp":"2025-08-31T17:48","system":"Auto","heatSetting":60,"coolSetting":85,"fan":"Auto","status":"Occupied","temperature":81.8,"humidity":0,"humidifySetting":0,"dehumidifySetting":0,"co2Setting":"","co2Level":"","setBy":"Schedule","frontKeypad":"On","runStatus":"Off","auxStatus":"Off","setback":"Off"},{"timestamp":"2025-08-31T18:00","system":"Auto","heatSetting":60,"coolSetting":85,"fan":"Auto","status":"Occupied","temperature":81.7,"humidity":0,"humidifySetting":0,"dehumidifySetting":0,"co2Setting":"","co2Level":"","setBy":"Schedule","frontKeypad":"On","runStatus":"Off","auxStatus":"Off","setback":"Off"},{"timestamp":"2025-08-31T18:10","system":"Auto","heatSetting":60,"coolSetting":85,"fan":"Auto","status":"Occupied","temperature":81.6,"humidity":0,"humidifySetting":0,"dehumidifySetting":0,"co2Setting":"","co2Level":"","setBy":"Schedule","frontKeypad":"On","runStatus":"Off","auxStatus":"Off","setback":"Off"},{"timestamp":"2025-08-31T18:25","system":"Auto","heatSetting":60,"coolSetting":85,"fan":"Auto","status":"Occupied","temperature":81.5,"humidity":0,"humidifySetting":0,"dehumidifySetting":0,"co2Setting":"","co2Level":"","setBy":"Schedule","frontKeypad":"On","runStatus":"Off","auxStatus":"Off","setback":"Off"},{"timestamp":"2025-08-31T18:38","system":"Auto","heatSetting":60,"coolSetting":85,"fan":"Auto","status":"Occupied","temperature":81.4,"humidity":0,"humidifySetting":0,"dehumidifySetting":0,"co2Setting":"","co2Level":"","setBy":"Schedule","frontKeypad":"On","runStatus":"Off","auxStatus":"Off","setback":"Off"},{"timestamp":"2025-08-31T18:55","system":"Auto","heatSetting":60,"coolSetting":85,"fan":"Auto","status":"Occupied","temperature":81.2,"humidity":0,"humidifySetting":0,"dehumidifySetting":0,"co2Setting":"","co2Level":"","setBy":"Schedule","frontKeypad":"On","runStatus":"Off","auxStatus":"Off","setback":"Off"},{"timestamp":"2025-08-31T19:03","system":"Auto","heatSetting":60,"coolSetting":85,"fan":"Auto","status":"Occupied","temperature":81.1,"humidity":0,"humidifySetting":0,"dehumidifySetting":0,"co2Setting":"","co2Level":"","setBy":"Schedule","frontKeypad":"On","runStatus":"Off","auxStatus":"Off","setback":"Off"},{"timestamp":"2025-08-31T19:15","system":"Auto","heatSetting":60,"coolSetting":85,"fan":"Auto","status":"Occupied","temperature":81,"humidity":0,"humidifySetting":0,"dehumidifySetting":0,"co2Setting":"","co2Level":"","setBy":"Schedule","frontKeypad":"On","runStatus":"Off","auxStatus":"Off","setback":"Off"},{"timestamp":"2025-08-31T19:36","system":"Auto","heatSetting":60,"coolSetting":85,"fan":"Auto","status":"Occupied","temperature":80.9,"humidity":0,"humidifySetting":0,"dehumidifySetting":0,"co2Setting":"","co2Level":"","setBy":"Schedule","frontKeypad":"On","runStatus":"Off","auxStatus":"Off","setback":"Off"},{"timestamp":"2025-08-31T19:38","system":"Auto","heatSetting":60,"coolSetting":85,"fan":"Auto","status":"Occupied","temperature":81,"humidity":0,"humidifySetting":0,"dehumidifySetting":0,"co2Setting":"","co2Level":"","setBy":"Schedule","frontKeypad":"On","runStatus":"Off","auxStatus":"Off","setback":"Off"},{"timestamp":"2025-08-31T19:40","system":"Auto","heatSetting":60,"coolSetting":85,"fan":"Auto","status":"Occupied","temperature":80.9,"humidity":0,"humidifySetting":0,"dehumidifySetting":0,"co2Setting":"","co2Level":"","setBy":"Schedule","frontKeypad":"On","runStatus":"Off","auxStatus":"Off","setback":"Off"},{"timestamp":"2025-08-31T19:52","system":"Auto","heatSetting":60,"coolSetting":85,"fan":"Auto","status":"Occupied","temperature":80.8,"humidity":0,"humidifySetting":0,"dehumidifySetting":0,"co2Setting":"","co2Level":"","setBy":"Schedule","frontKeypad":"On","runStatus":"Off","auxStatus":"Off","setback":"Off"},{"timestamp":"2025-08-31T20:00","system":"Auto","heatSetting":60,"coolSetting":85,"fan":"Auto","status":"Occupied","temperature":80.8,"humidity":0,"humidifySetting":0,"dehumidifySetting":0,"co2Setting":"","co2Level":"","setBy":"Schedule","frontKeypad":"On","runStatus":"Off","auxStatus":"Off","setback":"Off"},{"timestamp":"2025-08-31T20:18","system":"Auto","heatSetting":60,"coolSetting":85,"fan":"Auto","status":"Occupied","temperature":80.7,"humidity":0,"humidifySetting":0,"dehumidifySetting":0,"co2Setting":"","co2Level":"","setBy":"Schedule","frontKeypad":"On","runStatus":"Off","auxStatus":"Off","setback":"Off"},{"timestamp":"2025-08-31T20:23","system":"Auto","heatSetting":60,"coolSetting":85,"fan":"Auto","status":"Occupied","temperature":80.8,"humidity":0,"humidifySetting":0,"dehumidifySetting":0,"co2Setting":"","co2Level":"","setBy":"Schedule","frontKeypad":"On","runStatus":"Off","auxStatus":"Off","setback":"Off"},{"timestamp":"2025-08-31T20:28","system":"Auto","heatSetting":60,"coolSetting":85,"fan":"Auto","status":"Occupied","temperature":80.7,"humidity":0,"humidifySetting":0,"dehumidifySetting":0,"co2Setting":"","co2Level":"","setBy":"Schedule","frontKeypad":"On","runStatus":"Off","auxStatus":"Off","setback":"Off"},{"timestamp":"2025-08-31T20:56","system":"Auto","heatSetting":60,"coolSetting":85,"fan":"Auto","status":"Occupied","temperature":80.6,"humidity":0,"humidifySetting":0,"dehumidifySetting":0,"co2Setting":"","co2Level":"","setBy":"Schedule","frontKeypad":"On","runStatus":"Off","auxStatus":"Off","setback":"Off"},{"timestamp":"2025-08-31T21:20","system":"Auto","heatSetting":60,"coolSetting":85,"fan":"Auto","status":"Occupied","temperature":80.5,"humidity":0,"humidifySetting":0,"dehumidifySetting":0,"co2Setting":"","co2Level":"","setBy":"Schedule","frontKeypad":"On","runStatus":"Off","auxStatus":"Off","setback":"Off"},{"timestamp":"2025-08-31T21:52","system":"Auto","heatSetting":60,"coolSetting":85,"fan":"Auto","status":"Occupied","temperature":80.3,"humidity":0,"humidifySetting":0,"dehumidifySetting":0,"co2Setting":"","co2Level":"","setBy":"Schedule","frontKeypad":"On","runStatus":"Off","auxStatus":"Off","setback":"Off"},{"timestamp":"2025-08-31T22:00","system":"Auto","heatSetting":60,"coolSetting":85,"fan":"Auto","status":"Occupied","temperature":80.3,"humidity":0,"humidifySetting":0,"dehumidifySetting":0,"co2Setting":"","co2Level":"","setBy":"Schedule","frontKeypad":"On","runStatus":"Off","auxStatus":"Off","setback":"Off"},{"timestamp":"2025-08-31T22:01","system":"Auto","heatSetting":60,"coolSetting":85,"fan":"Auto","status":"Occupied","temperature":80.5,"humidity":0,"humidifySetting":0,"dehumidifySetting":0,"co2Setting":"","co2Level":"","setBy":"Schedule","frontKeypad":"On","runStatus":"Off","auxStatus":"Off","setback":"Off"},{"timestamp":"2025-08-31T22:06","system":"Auto","heatSetting":60,"coolSetting":85,"fan":"Auto","status":"Occupied","temperature":80.3,"humidity":0,"humidifySetting":0,"dehumidifySetting":0,"co2Setting":"","co2Level":"","setBy":"Schedule","frontKeypad":"On","runStatus":"Off","auxStatus":"Off","setback":"Off"},{"timestamp":"2025-08-31T22:28","system":"Auto","heatSetting":60,"coolSetting":85,"fan":"Auto","status":"Occupied","temperature":80.2,"humidity":0,"humidifySetting":0,"dehumidifySetting":0,"co2Setting":"","co2Level":"","setBy":"Schedule","frontKeypad":"On","runStatus":"Off","auxStatus":"Off","setback":"Off"},{"timestamp":"2025-08-31T22:34","system":"Auto","heatSetting":60,"coolSetting":85,"fan":"Auto","status":"Occupied","temperature":80.3,"humidity":0,"humidifySetting":0,"dehumidifySetting":0,"co2Setting":"","co2Level":"","setBy":"Schedule","frontKeypad":"On","runStatus":"Off","auxStatus":"Off","setback":"Off"},{"timestamp":"2025-08-31T22:39","system":"Auto","heatSetting":60,"coolSetting":85,"fan":"Auto","status":"Occupied","temperature":80.2,"humidity":0,"humidifySetting":0,"dehumidifySetting":0,"co2Setting":"","co2Level":"","setBy":"Schedule","frontKeypad":"On","runStatus":"Off","auxStatus":"Off","setback":"Off"},{"timestamp":"2025-08-31T23:00","system":"Auto","heatSetting":60,"coolSetting":85,"fan":"Auto","status":"Occupied","temperature":80.1,"humidity":0,"humidifySetting":0,"dehumidifySetting":0,"co2Setting":"","co2Level":"","setBy":"Schedule","frontKeypad":"On","runStatus":"Off","auxStatus":"Off","setback":"Off"},{"timestamp":"2025-08-31T23:37","system":"Auto","heatSetting":60,"coolSetting":85,"fan":"Auto","status":"Occupied","temperature":80,"humidity":0,"humidifySetting":0,"dehumidifySetting":0,"co2Setting":"","co2Level":"","setBy":"Schedule","frontKeypad":"On","runStatus":"Off","auxStatus":"Off","setback":"Off"},{"timestamp":"2025-08-31T23:42","system":"Auto","heatSetting":60,"coolSetting":85,"fan":"Auto","status":"Occupied","temperature":80.1,"humidity":0,"humidifySetting":0,"dehumidifySetting":0,"co2Setting":"","co2Level":"","setBy":"Schedule","frontKeypad":"On","runStatus":"Off","auxStatus":"Off","setback":"Off"},{"timestamp":"2025-08-31T23:48","system":"Auto","heatSetting":60,"coolSetting":85,"fan":"Auto","status":"Occupied","temperature":80,"humidity":0,"humidifySetting":0,"dehumidifySetting":0,"co2Setting":"","co2Level":"","setBy":"Schedule","frontKeypad":"On","runStatus":"Off","auxStatus":"Off","setback":"Off"}]}